Workbook
Name FECHA_CORTE: TABLERO!$H$8

Sheet PORTADA
B2: FORMATOS ADMINISTRATIVOS | E2: VERSIÓN 2.0 · MÉXICO
B4: CONTROL OPERATIVO SEMANAL
B6: Formato administrativo profesional · editable · listo para imprimir
C9: FÓRMULAS AUTOMÁTICAS | D9: LISTAS DESPLEGABLES | E9: HOJAS PROTEGIDAS | F9: LISTO PARA IMPRIMIR
B15: ¿QUÉ INCLUYE ESTE ARCHIVO?
B16: ▸ | C16: TABLERO | D16: Tablero ejecutivo: semáforo general, indicadores clave, gráficas y texto automático para el reporte semanal.
B17: ▸ | C17: ACTIVIDADES | D17: Registro semanal de actividades con responsable, fecha compromiso, avance y semáforo automático.
B18: ▸ | C18: PROYECTOS | D18: Seguimiento de proyectos: avance planeado vs. real, presupuesto ejercido y semáforo.
B19: ▸ | C19: PENDIENTES | D19: Lista de pendientes con origen, responsable, antigüedad y semáforo.
B20: ▸ | C20: RIESGOS | D20: Registro de riesgos con probabilidad, impacto, clasificación automática y matriz de calor.
B21: ▸ | C21: DECISIONES | D21: Decisiones que requiere la dirección: contexto, opciones, recomendación y fecha requerida.
B22: ▸ | C22: INDICADORES | D22: Indicadores con meta y 12 semanas de historia; cumplimiento y semáforo automáticos.
B23: ▸ | C23: CATÁLOGOS | D23: Listas editables (categorías, métodos, unidades) que alimentan los menús desplegables.
B24: ▸ | C24: AYUDA | D24: Preguntas frecuentes, glosario y lista de verificación para cerrar tu periodo.
B26: CÓMO USARLO
B27: 1 | C27: Define tus responsables, estatus y prioridades en la hoja CATÁLOGOS (todo el libro usa esas listas).
B28: 2 | C28: Captura cada semana tus ACTIVIDADES, PROYECTOS, PENDIENTES, RIESGOS, DECISIONES e INDICADORES; los semáforos se calculan solos.
B29: 3 | C29: La FECHA DE CORTE del TABLERO se actualiza con HOY; puedes escribir una fecha fija para cerrar una semana.
B30: 4 | C30: Lee el TABLERO: semáforo general, indicadores clave y gráficas. El texto de la celda B10 sirve de resumen para tu reporte semanal.
B31: 5 | C31: Envía a dirección el reporte semanal (formato Word incluido en el paquete) con los pendientes, riesgos y decisiones en rojo o ámbar.
B32: 6 | C32: Personaliza: inserta tu logotipo en el recuadro punteado de la esquina superior derecha (Insertar > Imágenes) y captura los datos de tu empresa en las celdas de captura.
B34: RECOMENDACIONES DE USO
B35: ✓ | C35: Actualiza el libro una vez por semana (por ejemplo, los viernes) antes de enviar el reporte a dirección.
B36: ✓ | C36: Cambia la FECHA DE CORTE del TABLERO (o déjala en HOY) y revisa los semáforos: todo lo rojo requiere acción o decisión.
B37: ✓ | C37: Un pendiente sin responsable y sin fecha no es un pendiente: asigna ambos antes de guardarlo.
B38: ✓ | C38: Registra riesgos antes de que ocurran; califica probabilidad e impacto de 1 a 5 y atiende primero los de nivel ALTO.
B39: ✓ | C39: Las decisiones requeridas deben llegar a la junta con contexto, opciones y una recomendación.
B40: ✓ | C40: Guarda una copia del archivo cada semana (Archivo > Guardar como) para conservar el historial.
B42: LEYENDA DE COLORES
C43: CELDA DE CAPTURA: escribe aquí.
C44: CÁLCULO AUTOMÁTICO: no la modifiques.
C45: ENCABEZADOS Y TÍTULOS.
B47: Formatos administrativos · Para uso interno de tu empresa

Sheet TABLERO
A1: TABLERO EJECUTIVO SEMANAL | H1: INSERTE SU LOGO (clic derecho > Insertar imagen)
A2: Lectura rápida para dirección: avances, pendientes, riesgos y decisiones
B4: ACTIVIDADES CUMPLIDAS | D4: ACTIVIDADES VENCIDAS | F4: PENDIENTES ABIERTOS | H4: RIESGOS ALTOS
B5: =IFERROR(COUNTIF(ACTIVIDADES!$I$5:$I$204,"TERMINADO")/COUNTA(ACTIVIDADES!$C$5:$C$204),0) | D5: =COUNTIF(ACTIVIDADES!$L$5:$L$204,"VENCIDO") | F5: =COUNTIFS(PENDIENTES!$H$5:$H$154,"<>TERMINADO",PENDIENTES!$B$5:$B$154,"<>") | H5: =COUNTIF(RIESGOS!$G$5:$G$64,"ALTO")
B7: DECISIONES PENDIENTES | D7: PROYECTOS EN ROJO | F7: SEMÁFORO GENERAL | H7: FECHA DE CORTE
B8: =COUNTIFS(DECISIONES!$H$5:$H$64,"PENDIENTE",DECISIONES!$B$5:$B$64,"<>") | D8: =COUNTIF(PROYECTOS!$M$5:$M$44,"ROJO") | F8: =IF(OR(D5>5,H5>2,D8>0),"ROJO",IF(OR(D5>0,H5>0,B8>0,F5>5),"ÁMBAR","VERDE")) | H8: 46302
B10: ="SEMANA AL "&TEXT(H8,"DD/MM/YYYY")&": "&TEXT(B5,"0%")&" DE LAS ACTIVIDADES CUMPLIDAS, "&D5&" VENCIDAS, "&F5&" PENDIENTES ABIERTOS, "&H5&" RIESGOS ALTOS, "&B8&" DECISIONES POR TOMAR Y "&D8&" PROYECTOS EN ROJO. SEMÁFORO GENERAL: "&F8&"."
B46: ESTATUS DE ACTIVIDADES | C46: ACTIVIDADES | E46: CLASIFICACIÓN DE RIESGOS | F46: RIESGOS
B47: PENDIENTE | C47: =COUNTIF(ACTIVIDADES!$I$5:$I$204,B47) | E47: ALTO | F47: =COUNTIF(RIESGOS!$G$5:$G$64,E47)
B48: EN PROCESO | C48: =COUNTIF(ACTIVIDADES!$I$5:$I$204,B48) | E48: MEDIO | F48: =COUNTIF(RIESGOS!$G$5:$G$64,E48)
B49: TERMINADO | C49: =COUNTIF(ACTIVIDADES!$I$5:$I$204,B49) | E49: BAJO | F49: =COUNTIF(RIESGOS!$G$5:$G$64,E49)
B50: BLOQUEADO | C50: =COUNTIF(ACTIVIDADES!$I$5:$I$204,B50)
B53: RESPONSABLE | C53: ASIGNADAS | D53: TERMINADAS | F53: PROYECTO | G53: AVANCE PLANEADO | H53: AVANCE REAL
B54: =IF('CATÁLOGOS'!B5="","",'CATÁLOGOS'!B5) | C54: =IF(B54="",0,COUNTIF(ACTIVIDADES!$E$5:$E$204,B54)) | D54: =IF(B54="",0,COUNTIFS(ACTIVIDADES!$E$5:$E$204,B54,ACTIVIDADES!$I$5:$I$204,"TERMINADO")) | F54: =IF(PROYECTOS!B5="","",LEFT(PROYECTOS!B5,26)) | G54: =IF(PROYECTOS!G5="",0,PROYECTOS!G5) | H54: =IF(PROYECTOS!H5="",0,PROYECTOS!H5)
B55: =IF('CATÁLOGOS'!B6="","",'CATÁLOGOS'!B6) | C55: =IF(B55="",0,COUNTIF(ACTIVIDADES!$E$5:$E$204,B55)) | D55: =IF(B55="",0,COUNTIFS(ACTIVIDADES!$E$5:$E$204,B55,ACTIVIDADES!$I$5:$I$204,"TERMINADO")) | F55: =IF(PROYECTOS!B6="","",LEFT(PROYECTOS!B6,26)) | G55: =IF(PROYECTOS!G6="",0,PROYECTOS!G6) | H55: =IF(PROYECTOS!H6="",0,PROYECTOS!H6)
B56: =IF('CATÁLOGOS'!B7="","",'CATÁLOGOS'!B7) | C56: =IF(B56="",0,COUNTIF(ACTIVIDADES!$E$5:$E$204,B56)) | D56: =IF(B56="",0,COUNTIFS(ACTIVIDADES!$E$5:$E$204,B56,ACTIVIDADES!$I$5:$I$204,"TERMINADO")) | F56: =IF(PROYECTOS!B7="","",LEFT(PROYECTOS!B7,26)) | G56: =IF(PROYECTOS!G7="",0,PROYECTOS!G7) | H56: =IF(PROYECTOS!H7="",0,PROYECTOS!H7)
B57: =IF('CATÁLOGOS'!B8="","",'CATÁLOGOS'!B8) | C57: =IF(B57="",0,COUNTIF(ACTIVIDADES!$E$5:$E$204,B57)) | D57: =IF(B57="",0,COUNTIFS(ACTIVIDADES!$E$5:$E$204,B57,ACTIVIDADES!$I$5:$I$204,"TERMINADO")) | F57: =IF(PROYECTOS!B8="","",LEFT(PROYECTOS!B8,26)) | G57: =IF(PROYECTOS!G8="",0,PROYECTOS!G8) | H57: =IF(PROYECTOS!H8="",0,PROYECTOS!H8)
B58: =IF('CATÁLOGOS'!B9="","",'CATÁLOGOS'!B9) | C58: =IF(B58="",0,COUNTIF(ACTIVIDADES!$E$5:$E$204,B58)) | D58: =IF(B58="",0,COUNTIFS(ACTIVIDADES!$E$5:$E$204,B58,ACTIVIDADES!$I$5:$I$204,"TERMINADO")) | F58: =IF(PROYECTOS!B9="","",LEFT(PROYECTOS!B9,26)) | G58: =IF(PROYECTOS!G9="",0,PROYECTOS!G9) | H58: =IF(PROYECTOS!H9="",0,PROYECTOS!H9)
B59: =IF('CATÁLOGOS'!B10="","",'CATÁLOGOS'!B10) | C59: =IF(B59="",0,COUNTIF(ACTIVIDADES!$E$5:$E$204,B59)) | D59: =IF(B59="",0,COUNTIFS(ACTIVIDADES!$E$5:$E$204,B59,ACTIVIDADES!$I$5:$I$204,"TERMINADO")) | F59: =IF(PROYECTOS!B10="","",LEFT(PROYECTOS!B10,26)) | G59: =IF(PROYECTOS!G10="",0,PROYECTOS!G10) | H59: =IF(PROYECTOS!H10="",0,PROYECTOS!H10)
B60: =IF('CATÁLOGOS'!B11="","",'CATÁLOGOS'!B11) | C60: =IF(B60="",0,COUNTIF(ACTIVIDADES!$E$5:$E$204,B60)) | D60: =IF(B60="",0,COUNTIFS(ACTIVIDADES!$E$5:$E$204,B60,ACTIVIDADES!$I$5:$I$204,"TERMINADO")) | F60: =IF(PROYECTOS!B11="","",LEFT(PROYECTOS!B11,26)) | G60: =IF(PROYECTOS!G11="",0,PROYECTOS!G11) | H60: =IF(PROYECTOS!H11="",0,PROYECTOS!H11)
B61: =IF('CATÁLOGOS'!B12="","",'CATÁLOGOS'!B12) | C61: =IF(B61="",0,COUNTIF(ACTIVIDADES!$E$5:$E$204,B61)) | D61: =IF(B61="",0,COUNTIFS(ACTIVIDADES!$E$5:$E$204,B61,ACTIVIDADES!$I$5:$I$204,"TERMINADO")) | F61: =IF(PROYECTOS!B12="","",LEFT(PROYECTOS!B12,26)) | G61: =IF(PROYECTOS!G12="",0,PROYECTOS!G12) | H61: =IF(PROYECTOS!H12="",0,PROYECTOS!H12)

Sheet ACTIVIDADES
A1: ACTIVIDADES DE LA SEMANA | M1: INSERTE SU LOGO (clic derecho > Insertar imagen)
A2: Registro semanal de actividades con semáforo automático
A4: NO. | B4: SEMANA (LUNES) | C4: ACTIVIDAD | D4: PROYECTO / ÁREA | E4: RESPONSABLE | F4: PRIORIDAD | G4: FECHA COMPROMISO | H4: FECHA REAL | I4: ESTATUS | J4: AVANCE | K4: DÍAS DE ATRASO | L4: SEMÁFORO | M4: EVIDENCIA / ENTREGABLE
A5: 1 | B5: 46300 | C5: CONCILIAR FACTURAS DE PROVEEDORES DE SEPTIEMBRE | D5: ADMINISTRACIÓN | E5: FINANZAS | F5: ALTA | G5: 46301 | H5: 46301 | I5: TERMINADO | J5: 1 | K5: =IF(OR(C5="",G5="",I5="TERMINADO"),"",MAX(0,FECHA_CORTE-G5)) | L5: =IF(C5="","",IF(I5="TERMINADO","CUMPLIDO",IF(G5="","SIN FECHA",IF(G5<FECHA_CORTE,"VENCIDO",IF(G5-FECHA_CORTE<=2,"POR VENCER","EN TIEMPO"))))) | M5: REPORTE DE CONCILIACIÓN
A6: 2 | B6: 46300 | C6: INTEGRAR EXPEDIENTE DE COMPRAS DE LA NAVE TOLUCA | D6: NAVE TOLUCA FASE 2 | E6: COMPRAS | F6: ALTA | G6: 46302 | I6: EN PROCESO | J6: 0.7 | K6: =IF(OR(C6="",G6="",I6="TERMINADO"),"",MAX(0,FECHA_CORTE-G6)) | L6: =IF(C6="","",IF(I6="TERMINADO","CUMPLIDO",IF(G6="","SIN FECHA",IF(G6<FECHA_CORTE,"VENCIDO",IF(G6-FECHA_CORTE<=2,"POR VENCER","EN TIEMPO"))))) | M6: EXPEDIENTE DIGITAL
A7: 3 | B7: 46300 | C7: PRESENTAR PROPUESTA DE CIERRE A CONSTRUCTORA ALTAMIRA | D7: REMODELACIÓN OFICINAS | E7: PROYECTOS | F7: ALTA | G7: 46304 | I7: EN PROCESO | J7: 0.5 | K7: =IF(OR(C7="",G7="",I7="TERMINADO"),"",MAX(0,FECHA_CORTE-G7)) | L7: =IF(C7="","",IF(I7="TERMINADO","CUMPLIDO",IF(G7="","SIN FECHA",IF(G7<FECHA_CORTE,"VENCIDO",IF(G7-FECHA_CORTE<=2,"POR VENCER","EN TIEMPO"))))) | M7: PRESENTACIÓN
A8: 4 | B8: 46300 | C8: CALCULAR NÓMINA DE LA SEGUNDA QUINCENA DE SEPTIEMBRE | D8: NÓMINA | E8: RECURSOS HUMANOS | F8: ALTA | G8: 46296 | H8: 46296 | I8: TERMINADO | J8: 1 | K8: =IF(OR(C8="",G8="",I8="TERMINADO"),"",MAX(0,FECHA_CORTE-G8)) | L8: =IF(C8="","",IF(I8="TERMINADO","CUMPLIDO",IF(G8="","SIN FECHA",IF(G8<FECHA_CORTE,"VENCIDO",IF(G8-FECHA_CORTE<=2,"POR VENCER","EN TIEMPO"))))) | M8: LAYOUT DE DISPERSIÓN
A9: 5 | B9: 46300 | C9: PRESENTAR DECLARACIÓN MENSUAL DE IVA | D9: CUMPLIMIENTO FISCAL | E9: FINANZAS | F9: ALTA | G9: 46300 | H9: 46300 | I9: TERMINADO | J9: 1 | K9: =IF(OR(C9="",G9="",I9="TERMINADO"),"",MAX(0,FECHA_CORTE-G9)) | L9: =IF(C9="","",IF(I9="TERMINADO","CUMPLIDO",IF(G9="","SIN FECHA",IF(G9<FECHA_CORTE,"VENCIDO",IF(G9-FECHA_CORTE<=2,"POR VENCER","EN TIEMPO"))))) | M9: ACUSE SAT
A10: 6 | B10: 46300 | C10: ENVIAR FACTURAS PENDIENTES DE TIMBRAR | D10: FACTURACIÓN | E10: ADMINISTRACIÓN | F10: MEDIA | G10: 46297 | I10: PENDIENTE | J10: 0 | K10: =IF(OR(C10="",G10="",I10="TERMINADO"),"",MAX(0,FECHA_CORTE-G10)) | L10: =IF(C10="","",IF(I10="TERMINADO","CUMPLIDO",IF(G10="","SIN FECHA",IF(G10<FECHA_CORTE,"VENCIDO",IF(G10-FECHA_CORTE<=2,"POR VENCER","EN TIEMPO")))))
A11: 7 | B11: 46300 | C11: DAR SEGUIMIENTO A COBRANZA MAYOR A 60 DÍAS | D11: COBRANZA | E11: FINANZAS | F11: ALTA | G11: 46301 | I11: EN PROCESO | J11: 0.4 | K11: =IF(OR(C11="",G11="",I11="TERMINADO"),"",MAX(0,FECHA_CORTE-G11)) | L11: =IF(C11="","",IF(I11="TERMINADO","CUMPLIDO",IF(G11="","SIN FECHA",IF(G11<FECHA_CORTE,"VENCIDO",IF(G11-FECHA_CORTE<=2,"POR VENCER","EN TIEMPO"))))) | M11: BITÁCORA DE LLAMADAS
A12: 8 | B12: 46300 | C12: VALIDAR ALTAS Y BAJAS DE IMSS DEL MES | D12: CUMPLIMIENTO IMSS | E12: RECURSOS HUMANOS | F12: MEDIA | G12: 46303 | I12: EN PROCESO | J12: 0.6 | K12: =IF(OR(C12="",G12="",I12="TERMINADO"),"",MAX(0,FECHA_CORTE-G12)) | L12: =IF(C12="","",IF(I12="TERMINADO","CUMPLIDO",IF(G12="","SIN FECHA",IF(G12<FECHA_CORTE,"VENCIDO",IF(G12-FECHA_CORTE<=2,"POR VENCER","EN TIEMPO"))))) | M12: CÉDULA IDSE
A13: 9 | B13: 46300 | C13: ACTUALIZAR PROGRAMA DE OBRA PLANTA QUERÉTARO | D13: CIERRE DE OBRA QUERÉTARO | E13: PROYECTOS | F13: ALTA | G13: 46302 | I13: BLOQUEADO | J13: 0.3 | K13: =IF(OR(C13="",G13="",I13="TERMINADO"),"",MAX(0,FECHA_CORTE-G13)) | L13: =IF(C13="","",IF(I13="TERMINADO","CUMPLIDO",IF(G13="","SIN FECHA",IF(G13<FECHA_CORTE,"VENCIDO",IF(G13-FECHA_CORTE<=2,"POR VENCER","EN TIEMPO"))))) | M13: PROGRAMA ACTUALIZADO
A14: 10 | B14: 46300 | C14: SOLICITAR COTIZACIONES DE ACERO ESTRUCTURAL | D14: NAVE TOLUCA FASE 2 | E14: COMPRAS | F14: MEDIA | G14: 46304 | I14: PENDIENTE | J14: 0 | K14: =IF(OR(C14="",G14="",I14="TERMINADO"),"",MAX(0,FECHA_CORTE-G14)) | L14: =IF(C14="","",IF(I14="TERMINADO","CUMPLIDO",IF(G14="","SIN FECHA",IF(G14<FECHA_CORTE,"VENCIDO",IF(G14-FECHA_CORTE<=2,"POR VENCER","EN TIEMPO")))))
A15: 11 | B15: 46300 | C15: ELABORAR REPORTE SEMANAL PARA DIRECCIÓN | D15: REPORTES | E15: ADMINISTRACIÓN | F15: ALTA | G15: 46304 | I15: PENDIENTE | J15: 0.2 | K15: =IF(OR(C15="",G15="",I15="TERMINADO"),"",MAX(0,FECHA_CORTE-G15)) | L15: =IF(C15="","",IF(I15="TERMINADO","CUMPLIDO",IF(G15="","SIN FECHA",IF(G15<FECHA_CORTE,"VENCIDO",IF(G15-FECHA_CORTE<=2,"POR VENCER","EN TIEMPO"))))) | M15: REPORTE SEMANAL
A16: 12 | B16: 46300 | C16: DOCUMENTAR EL PROCESO DE ALTA DE PROVEEDORES | D16: ERP ADMINISTRATIVO | E16: ADMINISTRACIÓN | F16: BAJA | G16: 46309 | I16: EN PROCESO | J16: 0.35 | K16: =IF(OR(C16="",G16="",I16="TERMINADO"),"",MAX(0,FECHA_CORTE-G16)) | L16: =IF(C16="","",IF(I16="TERMINADO","CUMPLIDO",IF(G16="","SIN FECHA",IF(G16<FECHA_CORTE,"VENCIDO",IF(G16-FECHA_CORTE<=2,"POR VENCER","EN TIEMPO"))))) | M16: PROCEDIMIENTO
A17: 13 | B17: 46300 | C17: CONCILIAR CAJA CHICA Y VIÁTICOS | D17: CONTROL FINANCIERO | E17: FINANZAS | F17: MEDIA | G17: 46300 | H17: 46301 | I17: TERMINADO | J17: 1 | K17: =IF(OR(C17="",G17="",I17="TERMINADO"),"",MAX(0,FECHA_CORTE-G17)) | L17: =IF(C17="","",IF(I17="TERMINADO","CUMPLIDO",IF(G17="","SIN FECHA",IF(G17<FECHA_CORTE,"VENCIDO",IF(G17-FECHA_CORTE<=2,"POR VENCER","EN TIEMPO"))))) | M17: ARQUEO FIRMADO
A18: 14 | B18: 46300 | C18: CAPACITAR A USUARIOS EN EL NUEVO MÓDULO DE COMPRAS | D18: ERP ADMINISTRATIVO | E18: OPERACIONES | F18: MEDIA | G18: 46307 | I18: PENDIENTE | J18: 0 | K18: =IF(OR(C18="",G18="",I18="TERMINADO"),"",MAX(0,FECHA_CORTE-G18)) | L18: =IF(C18="","",IF(I18="TERMINADO","CUMPLIDO",IF(G18="","SIN FECHA",IF(G18<FECHA_CORTE,"VENCIDO",IF(G18-FECHA_CORTE<=2,"POR VENCER","EN TIEMPO")))))
A19: 15 | B19: 46300 | C19: CERRAR EXPEDIENTE FOTOGRÁFICO DE LA OBRA | D19: CIERRE DE OBRA QUERÉTARO | E19: OPERACIONES | F19: ALTA | G19: 46298 | I19: EN PROCESO | J19: 0.8 | K19: =IF(OR(C19="",G19="",I19="TERMINADO"),"",MAX(0,FECHA_CORTE-G19)) | L19: =IF(C19="","",IF(I19="TERMINADO","CUMPLIDO",IF(G19="","SIN FECHA",IF(G19<FECHA_CORTE,"VENCIDO",IF(G19-FECHA_CORTE<=2,"POR VENCER","EN TIEMPO"))))) | M19: ÁLBUM DE EVIDENCIAS
A20: 16 | B20: 46300 | C20: REVISAR CONTRATOS DE SUBCONTRATISTAS | D20: NAVE TOLUCA FASE 2 | E20: DIRECCIÓN | F20: MEDIA | G20: 46303 | I20: EN PROCESO | J20: 0.5 | K20: =IF(OR(C20="",G20="",I20="TERMINADO"),"",MAX(0,FECHA_CORTE-G20)) | L20: =IF(C20="","",IF(I20="TERMINADO","CUMPLIDO",IF(G20="","SIN FECHA",IF(G20<FECHA_CORTE,"VENCIDO",IF(G20-FECHA_CORTE<=2,"POR VENCER","EN TIEMPO"))))) | M20: MATRIZ DE CONTRATOS
A21: 17 | B21: 46300 | C21: AUTORIZAR COMPRAS MAYORES A $50,000 | D21: COMPRAS | E21: DIRECCIÓN | F21: ALTA | G21: 46302 | H21: 46302 | I21: TERMINADO | J21: 1 | K21: =IF(OR(C21="",G21="",I21="TERMINADO"),"",MAX(0,FECHA_CORTE-G21)) | L21: =IF(C21="","",IF(I21="TERMINADO","CUMPLIDO",IF(G21="","SIN FECHA",IF(G21<FECHA_CORTE,"VENCIDO",IF(G21-FECHA_CORTE<=2,"POR VENCER","EN TIEMPO"))))) | M21: AUTORIZACIONES FIRMADAS
A22: 18 | B22: 46300 | C22: ACTUALIZAR INDICADORES SEMANALES | D22: TABLERO | E22: ADMINISTRACIÓN | F22: MEDIA | G22: 46304 | I22: PENDIENTE | J22: 0 | K22: =IF(OR(C22="",G22="",I22="TERMINADO"),"",MAX(0,FECHA_CORTE-G22)) | L22: =IF(C22="","",IF(I22="TERMINADO","CUMPLIDO",IF(G22="","SIN FECHA",IF(G22<FECHA_CORTE,"VENCIDO",IF(G22-FECHA_CORTE<=2,"POR VENCER","EN TIEMPO")))))
A23: 19 | K23: =IF(OR(C23="",G23="",I23="TERMINADO"),"",MAX(0,FECHA_CORTE-G23)) | L23: =IF(C23="","",IF(I23="TERMINADO","CUMPLIDO",IF(G23="","SIN FECHA",IF(G23<FECHA_CORTE,"VENCIDO",IF(G23-FECHA_CORTE<=2,"POR VENCER","EN TIEMPO")))))
A24: 20 | K24: =IF(OR(C24="",G24="",I24="TERMINADO"),"",MAX(0,FECHA_CORTE-G24)) | L24: =IF(C24="","",IF(I24="TERMINADO","CUMPLIDO",IF(G24="","SIN FECHA",IF(G24<FECHA_CORTE,"VENCIDO",IF(G24-FECHA_CORTE<=2,"POR VENCER","EN TIEMPO")))))
A25: 21 | K25: =IF(OR(C25="",G25="",I25="TERMINADO"),"",MAX(0,FECHA_CORTE-G25)) | L25: =IF(C25="","",IF(I25="TERMINADO","CUMPLIDO",IF(G25="","SIN FECHA",IF(G25<FECHA_CORTE,"VENCIDO",IF(G25-FECHA_CORTE<=2,"POR VENCER","EN TIEMPO")))))
A26: 22 | K26: =IF(OR(C26="",G26="",I26="TERMINADO"),"",MAX(0,FECHA_CORTE-G26)) | L26: =IF(C26="","",IF(I26="TERMINADO","CUMPLIDO",IF(G26="","SIN FECHA",IF(G26<FECHA_CORTE,"VENCIDO",IF(G26-FECHA_CORTE<=2,"POR VENCER","EN TIEMPO")))))
A27: 23 | K27: =IF(OR(C27="",G27="",I27="TERMINADO"),"",MAX(0,FECHA_CORTE-G27)) | L27: =IF(C27="","",IF(I27="TERMINADO","CUMPLIDO",IF(G27="","SIN FECHA",IF(G27<FECHA_CORTE,"VENCIDO",IF(G27-FECHA_CORTE<=2,"POR VENCER","EN TIEMPO")))))
A28: 24 | K28: =IF(OR(C28="",G28="",I28="TERMINADO"),"",MAX(0,FECHA_CORTE-G28)) | L28: =IF(C28="","",IF(I28="TERMINADO","CUMPLIDO",IF(G28="","SIN FECHA",IF(G28<FECHA_CORTE,"VENCIDO",IF(G28-FECHA_CORTE<=2,"POR VENCER","EN TIEMPO")))))
A29: 25 | K29: =IF(OR(C29="",G29="",I29="TERMINADO"),"",MAX(0,FECHA_CORTE-G29)) | L29: =IF(C29="","",IF(I29="TERMINADO","CUMPLIDO",IF(G29="","SIN FECHA",IF(G29<FECHA_CORTE,"VENCIDO",IF(G29-FECHA_CORTE<=2,"POR VENCER","EN TIEMPO")))))
A30: 26 | K30: =IF(OR(C30="",G30="",I30="TERMINADO"),"",MAX(0,FECHA_CORTE-G30)) | L30: =IF(C30="","",IF(I30="TERMINADO","CUMPLIDO",IF(G30="","SIN FECHA",IF(G30<FECHA_CORTE,"VENCIDO",IF(G30-FECHA_CORTE<=2,"POR VENCER","EN TIEMPO")))))
A31: 27 | K31: =IF(OR(C31="",G31="",I31="TERMINADO"),"",MAX(0,FECHA_CORTE-G31)) | L31: =IF(C31="","",IF(I31="TERMINADO","CUMPLIDO",IF(G31="","SIN FECHA",IF(G31<FECHA_CORTE,"VENCIDO",IF(G31-FECHA_CORTE<=2,"POR VENCER","EN TIEMPO")))))
A32: 28 | K32: =IF(OR(C32="",G32="",I32="TERMINADO"),"",MAX(0,FECHA_CORTE-G32)) | L32: =IF(C32="","",IF(I32="TERMINADO","CUMPLIDO",IF(G32="","SIN FECHA",IF(G32<FECHA_CORTE,"VENCIDO",IF(G32-FECHA_CORTE<=2,"POR VENCER","EN TIEMPO")))))
A33: 29 | K33: =IF(OR(C33="",G33="",I33="TERMINADO"),"",MAX(0,FECHA_CORTE-G33)) | L33: =IF(C33="","",IF(I33="TERMINADO","CUMPLIDO",IF(G33="","SIN FECHA",IF(G33<FECHA_CORTE,"VENCIDO",IF(G33-FECHA_CORTE<=2,"POR VENCER","EN TIEMPO")))))
A34: 30 | K34: =IF(OR(C34="",G34="",I34="TERMINADO"),"",MAX(0,FECHA_CORTE-G34)) | L34: =IF(C34="","",IF(I34="TERMINADO","CUMPLIDO",IF(G34="","SIN FECHA",IF(G34<FECHA_CORTE,"VENCIDO",IF(G34-FECHA_CORTE<=2,"POR VENCER","EN TIEMPO")))))
... A204: 200 | K204: =IF(OR(C204="",G204="",I204="TERMINADO"),"",MAX(0,FECHA_CORTE-G204)) | L204: =IF(C204="","",IF(I204="TERMINADO","CUMPLIDO",IF(G204="","SIN FECHA",IF(G204<FECHA_CORTE,"VENCIDO",IF(G204-FECHA_CORTE<=2,"POR VENCER","EN TIEMPO")))))

Sheet PROYECTOS
A1: SEGUIMIENTO DE PROYECTOS | O1: INSERTE SU LOGO (clic derecho > Insertar imagen)
A2: Avance planeado vs. real y presupuesto ejercido
A4: NO. | B4: PROYECTO | C4: CLIENTE / ÁREA | D4: RESPONSABLE | E4: INICIO | F4: FIN PLANEADO | G4: AVANCE PLANEADO | H4: AVANCE REAL | I4: PRESUPUESTO | J4: GASTO REAL | K4: % PRESUPUESTO EJERCIDO | L4: DESVIACIÓN DE AVANCE | M4: SEMÁFORO | N4: ESTATUS | O4: COMENTARIOS
A5: 1 | B5: NAVE INDUSTRIAL TOLUCA - FASE 2 | C5: GRUPO INDUSTRIAL DEL NORTE | D5: PROYECTOS | E5: 46204 | F5: 46371 | G5: =IF(OR(E5="",F5=""),"",MAX(0,MIN(1,(FECHA_CORTE-E5)/MAX(1,F5-E5)))) | H5: 0.42 | I5: 4800000 | J5: 2350000 | K5: =IF(OR(I5="",J5="",I5=0),"",J5/I5) | L5: =IF(OR(G5="",H5=""),"",H5-G5) | M5: =IF(B5="","",IF(N5="TERMINADO","VERDE",IF(L5="","",IF(OR(L5<-0.15,AND(K5<>"",K5>1.05)),"ROJO",IF(OR(L5<-0.05,AND(K5<>"",K5>1)),"ÁMBAR","VERDE"))))) | N5: EN PROCESO
A6: 2 | B6: REMODELACIÓN DE OFICINAS CORPORATIVAS | C6: CONSTRUCTORA ALTAMIRA | D6: OPERACIONES | E6: 46244 | F6: 46346 | G6: =IF(OR(E6="",F6=""),"",MAX(0,MIN(1,(FECHA_CORTE-E6)/MAX(1,F6-E6)))) | H6: 0.55 | I6: 1250000 | J6: 640000 | K6: =IF(OR(I6="",J6="",I6=0),"",J6/I6) | L6: =IF(OR(G6="",H6=""),"",H6-G6) | M6: =IF(B6="","",IF(N6="TERMINADO","VERDE",IF(L6="","",IF(OR(L6<-0.15,AND(K6<>"",K6>1.05)),"ROJO",IF(OR(L6<-0.05,AND(K6<>"",K6>1)),"ÁMBAR","VERDE"))))) | N6: EN PROCESO
A7: 3 | B7: IMPLEMENTACIÓN DE ERP ADMINISTRATIVO | C7: ADMINISTRACIÓN | D7: ADMINISTRACIÓN | E7: 46266 | F7: 46387 | G7: =IF(OR(E7="",F7=""),"",MAX(0,MIN(1,(FECHA_CORTE-E7)/MAX(1,F7-E7)))) | H7: 0.18 | I7: 780000 | J7: 210000 | K7: =IF(OR(I7="",J7="",I7=0),"",J7/I7) | L7: =IF(OR(G7="",H7=""),"",H7-G7) | M7: =IF(B7="","",IF(N7="TERMINADO","VERDE",IF(L7="","",IF(OR(L7<-0.15,AND(K7<>"",K7>1.05)),"ROJO",IF(OR(L7<-0.05,AND(K7<>"",K7>1)),"ÁMBAR","VERDE"))))) | N7: EN PROCESO
A8: 4 | B8: AUDITORÍA DE CUMPLIMIENTO IMSS | C8: RECURSOS HUMANOS | D8: RECURSOS HUMANOS | E8: 46280 | F8: 46325 | G8: =IF(OR(E8="",F8=""),"",MAX(0,MIN(1,(FECHA_CORTE-E8)/MAX(1,F8-E8)))) | H8: 0.7 | I8: 120000 | J8: 95000 | K8: =IF(OR(I8="",J8="",I8=0),"",J8/I8) | L8: =IF(OR(G8="",H8=""),"",H8-G8) | M8: =IF(B8="","",IF(N8="TERMINADO","VERDE",IF(L8="","",IF(OR(L8<-0.15,AND(K8<>"",K8>1.05)),"ROJO",IF(OR(L8<-0.05,AND(K8<>"",K8>1)),"ÁMBAR","VERDE"))))) | N8: EN PROCESO
A9: 5 | B9: CIERRE DE OBRA PLANTA QUERÉTARO | C9: OPERACIONES | D9: PROYECTOS | E9: 46146 | F9: 46304 | G9: =IF(OR(E9="",F9=""),"",MAX(0,MIN(1,(FECHA_CORTE-E9)/MAX(1,F9-E9)))) | H9: 0.78 | I9: 3100000 | J9: 3020000 | K9: =IF(OR(I9="",J9="",I9=0),"",J9/I9) | L9: =IF(OR(G9="",H9=""),"",H9-G9) | M9: =IF(B9="","",IF(N9="TERMINADO","VERDE",IF(L9="","",IF(OR(L9<-0.15,AND(K9<>"",K9>1.05)),"ROJO",IF(OR(L9<-0.05,AND(K9<>"",K9>1)),"ÁMBAR","VERDE"))))) | N9: EN PROCESO
A10: 6 | G10: =IF(OR(E10="",F10=""),"",MAX(0,MIN(1,(FECHA_CORTE-E10)/MAX(1,F10-E10)))) | K10: =IF(OR(I10="",J10="",I10=0),"",J10/I10) | L10: =IF(OR(G10="",H10=""),"",H10-G10) | M10: =IF(B10="","",IF(N10="TERMINADO","VERDE",IF(L10="","",IF(OR(L10<-0.15,AND(K10<>"",K10>1.05)),"ROJO",IF(OR(L10<-0.05,AND(K10<>"",K10>1)),"ÁMBAR","VERDE")))))
A11: 7 | G11: =IF(OR(E11="",F11=""),"",MAX(0,MIN(1,(FECHA_CORTE-E11)/MAX(1,F11-E11)))) | K11: =IF(OR(I11="",J11="",I11=0),"",J11/I11) | L11: =IF(OR(G11="",H11=""),"",H11-G11) | M11: =IF(B11="","",IF(N11="TERMINADO","VERDE",IF(L11="","",IF(OR(L11<-0.15,AND(K11<>"",K11>1.05)),"ROJO",IF(OR(L11<-0.05,AND(K11<>"",K11>1)),"ÁMBAR","VERDE")))))
A12: 8 | G12: =IF(OR(E12="",F12=""),"",MAX(0,MIN(1,(FECHA_CORTE-E12)/MAX(1,F12-E12)))) | K12: =IF(OR(I12="",J12="",I12=0),"",J12/I12) | L12: =IF(OR(G12="",H12=""),"",H12-G12) | M12: =IF(B12="","",IF(N12="TERMINADO","VERDE",IF(L12="","",IF(OR(L12<-0.15,AND(K12<>"",K12>1.05)),"ROJO",IF(OR(L12<-0.05,AND(K12<>"",K12>1)),"ÁMBAR","VERDE")))))
A13: 9 | G13: =IF(OR(E13="",F13=""),"",MAX(0,MIN(1,(FECHA_CORTE-E13)/MAX(1,F13-E13)))) | K13: =IF(OR(I13="",J13="",I13=0),"",J13/I13) | L13: =IF(OR(G13="",H13=""),"",H13-G13) | M13: =IF(B13="","",IF(N13="TERMINADO","VERDE",IF(L13="","",IF(OR(L13<-0.15,AND(K13<>"",K13>1.05)),"ROJO",IF(OR(L13<-0.05,AND(K13<>"",K13>1)),"ÁMBAR","VERDE")))))
A14: 10 | G14: =IF(OR(E14="",F14=""),"",MAX(0,MIN(1,(FECHA_CORTE-E14)/MAX(1,F14-E14)))) | K14: =IF(OR(I14="",J14="",I14=0),"",J14/I14) | L14: =IF(OR(G14="",H14=""),"",H14-G14) | M14: =IF(B14="","",IF(N14="TERMINADO","VERDE",IF(L14="","",IF(OR(L14<-0.15,AND(K14<>"",K14>1.05)),"ROJO",IF(OR(L14<-0.05,AND(K14<>"",K14>1)),"ÁMBAR","VERDE")))))
A15: 11 | G15: =IF(OR(E15="",F15=""),"",MAX(0,MIN(1,(FECHA_CORTE-E15)/MAX(1,F15-E15)))) | K15: =IF(OR(I15="",J15="",I15=0),"",J15/I15) | L15: =IF(OR(G15="",H15=""),"",H15-G15) | M15: =IF(B15="","",IF(N15="TERMINADO","VERDE",IF(L15="","",IF(OR(L15<-0.15,AND(K15<>"",K15>1.05)),"ROJO",IF(OR(L15<-0.05,AND(K15<>"",K15>1)),"ÁMBAR","VERDE")))))
A16: 12 | G16: =IF(OR(E16="",F16=""),"",MAX(0,MIN(1,(FECHA_CORTE-E16)/MAX(1,F16-E16)))) | K16: =IF(OR(I16="",J16="",I16=0),"",J16/I16) | L16: =IF(OR(G16="",H16=""),"",H16-G16) | M16: =IF(B16="","",IF(N16="TERMINADO","VERDE",IF(L16="","",IF(OR(L16<-0.15,AND(K16<>"",K16>1.05)),"ROJO",IF(OR(L16<-0.05,AND(K16<>"",K16>1)),"ÁMBAR","VERDE")))))
A17: 13 | G17: =IF(OR(E17="",F17=""),"",MAX(0,MIN(1,(FECHA_CORTE-E17)/MAX(1,F17-E17)))) | K17: =IF(OR(I17="",J17="",I17=0),"",J17/I17) | L17: =IF(OR(G17="",H17=""),"",H17-G17) | M17: =IF(B17="","",IF(N17="TERMINADO","VERDE",IF(L17="","",IF(OR(L17<-0.15,AND(K17<>"",K17>1.05)),"ROJO",IF(OR(L17<-0.05,AND(K17<>"",K17>1)),"ÁMBAR","VERDE")))))
A18: 14 | G18: =IF(OR(E18="",F18=""),"",MAX(0,MIN(1,(FECHA_CORTE-E18)/MAX(1,F18-E18)))) | K18: =IF(OR(I18="",J18="",I18=0),"",J18/I18) | L18: =IF(OR(G18="",H18=""),"",H18-G18) | M18: =IF(B18="","",IF(N18="TERMINADO","VERDE",IF(L18="","",IF(OR(L18<-0.15,AND(K18<>"",K18>1.05)),"ROJO",IF(OR(L18<-0.05,AND(K18<>"",K18>1)),"ÁMBAR","VERDE")))))
A19: 15 | G19: =IF(OR(E19="",F19=""),"",MAX(0,MIN(1,(FECHA_CORTE-E19)/MAX(1,F19-E19)))) | K19: =IF(OR(I19="",J19="",I19=0),"",J19/I19) | L19: =IF(OR(G19="",H19=""),"",H19-G19) | M19: =IF(B19="","",IF(N19="TERMINADO","VERDE",IF(L19="","",IF(OR(L19<-0.15,AND(K19<>"",K19>1.05)),"ROJO",IF(OR(L19<-0.05,AND(K19<>"",K19>1)),"ÁMBAR","VERDE")))))
A20: 16 | G20: =IF(OR(E20="",F20=""),"",MAX(0,MIN(1,(FECHA_CORTE-E20)/MAX(1,F20-E20)))) | K20: =IF(OR(I20="",J20="",I20=0),"",J20/I20) | L20: =IF(OR(G20="",H20=""),"",H20-G20) | M20: =IF(B20="","",IF(N20="TERMINADO","VERDE",IF(L20="","",IF(OR(L20<-0.15,AND(K20<>"",K20>1.05)),"ROJO",IF(OR(L20<-0.05,AND(K20<>"",K20>1)),"ÁMBAR","VERDE")))))
A21: 17 | G21: =IF(OR(E21="",F21=""),"",MAX(0,MIN(1,(FECHA_CORTE-E21)/MAX(1,F21-E21)))) | K21: =IF(OR(I21="",J21="",I21=0),"",J21/I21) | L21: =IF(OR(G21="",H21=""),"",H21-G21) | M21: =IF(B21="","",IF(N21="TERMINADO","VERDE",IF(L21="","",IF(OR(L21<-0.15,AND(K21<>"",K21>1.05)),"ROJO",IF(OR(L21<-0.05,AND(K21<>"",K21>1)),"ÁMBAR","VERDE")))))
... A44: 40 | G44: =IF(OR(E44="",F44=""),"",MAX(0,MIN(1,(FECHA_CORTE-E44)/MAX(1,F44-E44)))) | K44: =IF(OR(I44="",J44="",I44=0),"",J44/I44) | L44: =IF(OR(G44="",H44=""),"",H44-G44) | M44: =IF(B44="","",IF(N44="TERMINADO","VERDE",IF(L44="","",IF(OR(L44<-0.15,AND(K44<>"",K44>1.05)),"ROJO",IF(OR(L44<-0.05,AND(K44<>"",K44>1)),"ÁMBAR","VERDE")))))

Sheet PENDIENTES
A1: PENDIENTES ABIERTOS | K1: INSERTE SU LOGO (clic derecho > Insertar imagen)
A2: Lo que no se cierra, se acumula: responsable, fecha y semáforo
A4: NO. | B4: PENDIENTE | C4: ORIGEN (CLIENTE, JUNTA, DIRECCIÓN) | D4: RESPONSABLE | E4: PRIORIDAD | F4: FECHA SOLICITUD | G4: FECHA COMPROMISO | H4: ESTATUS | I4: DÍAS ABIERTOS | J4: SEMÁFORO | K4: COMENTARIOS
A5: 1 | B5: ENTREGAR ACTA DE ENTREGA-RECEPCIÓN FIRMADA | C5: CLIENTE ALTAMIRA | D5: PROYECTOS | E5: ALTA | F5: 46293 | G5: 46301 | H5: EN PROCESO | I5: =IF(OR(B5="",F5=""),"",MAX(0,FECHA_CORTE-F5)) | J5: =IF(B5="","",IF(H5="TERMINADO","CUMPLIDO",IF(G5="","SIN FECHA",IF(G5<FECHA_CORTE,"VENCIDO",IF(G5-FECHA_CORTE<=2,"POR VENCER","EN TIEMPO"))))) | K5: FALTA FIRMA DEL RESIDENTE
A6: 2 | B6: DEFINIR PROVEEDOR DE ACERO ESTRUCTURAL | C6: JUNTA SEMANAL | D6: COMPRAS | E6: ALTA | F6: 46295 | G6: 46304 | H6: PENDIENTE | I6: =IF(OR(B6="",F6=""),"",MAX(0,FECHA_CORTE-F6)) | J6: =IF(B6="","",IF(H6="TERMINADO","CUMPLIDO",IF(G6="","SIN FECHA",IF(G6<FECHA_CORTE,"VENCIDO",IF(G6-FECHA_CORTE<=2,"POR VENCER","EN TIEMPO"))))) | K6: ESPERANDO 3A COTIZACIÓN
A7: 3 | B7: REGULARIZAR PAGO DE CUOTAS IMSS DE AGOSTO | C7: AUDITORÍA | D7: RECURSOS HUMANOS | E7: ALTA | F7: 46287 | G7: 46297 | H7: EN PROCESO | I7: =IF(OR(B7="",F7=""),"",MAX(0,FECHA_CORTE-F7)) | J7: =IF(B7="","",IF(H7="TERMINADO","CUMPLIDO",IF(G7="","SIN FECHA",IF(G7<FECHA_CORTE,"VENCIDO",IF(G7-FECHA_CORTE<=2,"POR VENCER","EN TIEMPO"))))) | K7: PENDIENTE COMPROBANTE BANCARIO
A8: 4 | B8: ACTUALIZAR CONTRATO MARCO CON PROVEEDOR DE CONCRETO | C8: DIRECCIÓN | D8: DIRECCIÓN | E8: MEDIA | F8: 46280 | G8: 46315 | H8: PENDIENTE | I8: =IF(OR(B8="",F8=""),"",MAX(0,FECHA_CORTE-F8)) | J8: =IF(B8="","",IF(H8="TERMINADO","CUMPLIDO",IF(G8="","SIN FECHA",IF(G8<FECHA_CORTE,"VENCIDO",IF(G8-FECHA_CORTE<=2,"POR VENCER","EN TIEMPO")))))
A9: 5 | B9: ENVIAR ESTADO DE CUENTA A CLIENTES CON SALDO VENCIDO | C9: FINANZAS | D9: FINANZAS | E9: MEDIA | F9: 46296 | G9: 46303 | H9: EN PROCESO | I9: =IF(OR(B9="",F9=""),"",MAX(0,FECHA_CORTE-F9)) | J9: =IF(B9="","",IF(H9="TERMINADO","CUMPLIDO",IF(G9="","SIN FECHA",IF(G9<FECHA_CORTE,"VENCIDO",IF(G9-FECHA_CORTE<=2,"POR VENCER","EN TIEMPO")))))
A10: 6 | B10: CARGAR FACTURAS DE GASTOS DE SEPTIEMBRE | C10: CONTABILIDAD | D10: ADMINISTRACIÓN | E10: BAJA | F10: 46297 | G10: 46307 | H10: PENDIENTE | I10: =IF(OR(B10="",F10=""),"",MAX(0,FECHA_CORTE-F10)) | J10: =IF(B10="","",IF(H10="TERMINADO","CUMPLIDO",IF(G10="","SIN FECHA",IF(G10<FECHA_CORTE,"VENCIDO",IF(G10-FECHA_CORTE<=2,"POR VENCER","EN TIEMPO")))))
A11: 7 | B11: RESOLVER DIFERENCIA DE INVENTARIO EN BODEGA 2 | C11: OPERACIONES | D11: OPERACIONES | E11: MEDIA | F11: 46290 | G11: 46300 | H11: TERMINADO | I11: =IF(OR(B11="",F11=""),"",MAX(0,FECHA_CORTE-F11)) | J11: =IF(B11="","",IF(H11="TERMINADO","CUMPLIDO",IF(G11="","SIN FECHA",IF(G11<FECHA_CORTE,"VENCIDO",IF(G11-FECHA_CORTE<=2,"POR VENCER","EN TIEMPO"))))) | K11: AJUSTE AUTORIZADO
A12: 8 | I12: =IF(OR(B12="",F12=""),"",MAX(0,FECHA_CORTE-F12)) | J12: =IF(B12="","",IF(H12="TERMINADO","CUMPLIDO",IF(G12="","SIN FECHA",IF(G12<FECHA_CORTE,"VENCIDO",IF(G12-FECHA_CORTE<=2,"POR VENCER","EN TIEMPO")))))
A13: 9 | I13: =IF(OR(B13="",F13=""),"",MAX(0,FECHA_CORTE-F13)) | J13: =IF(B13="","",IF(H13="TERMINADO","CUMPLIDO",IF(G13="","SIN FECHA",IF(G13<FECHA_CORTE,"VENCIDO",IF(G13-FECHA_CORTE<=2,"POR VENCER","EN TIEMPO")))))
A14: 10 | I14: =IF(OR(B14="",F14=""),"",MAX(0,FECHA_CORTE-F14)) | J14: =IF(B14="","",IF(H14="TERMINADO","CUMPLIDO",IF(G14="","SIN FECHA",IF(G14<FECHA_CORTE,"VENCIDO",IF(G14-FECHA_CORTE<=2,"POR VENCER","EN TIEMPO")))))
A15: 11 | I15: =IF(OR(B15="",F15=""),"",MAX(0,FECHA_CORTE-F15)) | J15: =IF(B15="","",IF(H15="TERMINADO","CUMPLIDO",IF(G15="","SIN FECHA",IF(G15<FECHA_CORTE,"VENCIDO",IF(G15-FECHA_CORTE<=2,"POR VENCER","EN TIEMPO")))))
A16: 12 | I16: =IF(OR(B16="",F16=""),"",MAX(0,FECHA_CORTE-F16)) | J16: =IF(B16="","",IF(H16="TERMINADO","CUMPLIDO",IF(G16="","SIN FECHA",IF(G16<FECHA_CORTE,"VENCIDO",IF(G16-FECHA_CORTE<=2,"POR VENCER","EN TIEMPO")))))
A17: 13 | I17: =IF(OR(B17="",F17=""),"",MAX(0,FECHA_CORTE-F17)) | J17: =IF(B17="","",IF(H17="TERMINADO","CUMPLIDO",IF(G17="","SIN FECHA",IF(G17<FECHA_CORTE,"VENCIDO",IF(G17-FECHA_CORTE<=2,"POR VENCER","EN TIEMPO")))))
A18: 14 | I18: =IF(OR(B18="",F18=""),"",MAX(0,FECHA_CORTE-F18)) | J18: =IF(B18="","",IF(H18="TERMINADO","CUMPLIDO",IF(G18="","SIN FECHA",IF(G18<FECHA_CORTE,"VENCIDO",IF(G18-FECHA_CORTE<=2,"POR VENCER","EN TIEMPO")))))
A19: 15 | I19: =IF(OR(B19="",F19=""),"",MAX(0,FECHA_CORTE-F19)) | J19: =IF(B19="","",IF(H19="TERMINADO","CUMPLIDO",IF(G19="","SIN FECHA",IF(G19<FECHA_CORTE,"VENCIDO",IF(G19-FECHA_CORTE<=2,"POR VENCER","EN TIEMPO")))))
A20: 16 | I20: =IF(OR(B20="",F20=""),"",MAX(0,FECHA_CORTE-F20)) | J20: =IF(B20="","",IF(H20="TERMINADO","CUMPLIDO",IF(G20="","SIN FECHA",IF(G20<FECHA_CORTE,"VENCIDO",IF(G20-FECHA_CORTE<=2,"POR VENCER","EN TIEMPO")))))
A21: 17 | I21: =IF(OR(B21="",F21=""),"",MAX(0,FECHA_CORTE-F21)) | J21: =IF(B21="","",IF(H21="TERMINADO","CUMPLIDO",IF(G21="","SIN FECHA",IF(G21<FECHA_CORTE,"VENCIDO",IF(G21-FECHA_CORTE<=2,"POR VENCER","EN TIEMPO")))))
A22: 18 | I22: =IF(OR(B22="",F22=""),"",MAX(0,FECHA_CORTE-F22)) | J22: =IF(B22="","",IF(H22="TERMINADO","CUMPLIDO",IF(G22="","SIN FECHA",IF(G22<FECHA_CORTE,"VENCIDO",IF(G22-FECHA_CORTE<=2,"POR VENCER","EN TIEMPO")))))
A23: 19 | I23: =IF(OR(B23="",F23=""),"",MAX(0,FECHA_CORTE-F23)) | J23: =IF(B23="","",IF(H23="TERMINADO","CUMPLIDO",IF(G23="","SIN FECHA",IF(G23<FECHA_CORTE,"VENCIDO",IF(G23-FECHA_CORTE<=2,"POR VENCER","EN TIEMPO")))))
... A154: 150 | I154: =IF(OR(B154="",F154=""),"",MAX(0,FECHA_CORTE-F154)) | J154: =IF(B154="","",IF(H154="TERMINADO","CUMPLIDO",IF(G154="","SIN FECHA",IF(G154<FECHA_CORTE,"VENCIDO",IF(G154-FECHA_CORTE<=2,"POR VENCER","EN TIEMPO")))))

Sheet RIESGOS
A1: REGISTRO DE RIESGOS | J1: INSERTE SU LOGO (clic derecho > Insertar imagen)
A2: Probabilidad x impacto con clasificación automática y matriz de calor
M3: MATRIZ DE RIESGOS (CANTIDAD)
A4: NO. | B4: RIESGO | C4: PROYECTO / ÁREA | D4: PROBABILIDAD (1-5) | E4: IMPACTO (1-5) | F4: NIVEL (P X I) | G4: CLASIFICACIÓN | H4: RESPONSABLE | I4: ACCIÓN DE MITIGACIÓN | J4: FECHA LÍMITE | K4: ESTATUS | M4: PROB. \ IMPACTO | N4: 1 | O4: 2 | P4: 3 | Q4: 4 | R4: 5
A5: 1 | B5: RETRASO EN ENTREGA DE ACERO ESTRUCTURAL | C5: NAVE TOLUCA FASE 2 | D5: 4 | E5: 5 | F5: =IF(OR(D5="",E5=""),"",D5*E5) | G5: =IF(F5="","",IF(F5>=15,"ALTO",IF(F5>=8,"MEDIO","BAJO"))) | H5: COMPRAS | I5: COTIZAR CON DOS PROVEEDORES ALTERNOS Y FIJAR PENALIZACIÓN | J5: 46310 | K5: EN MITIGACIÓN | M5: 5 | N5: =COUNTIFS($D$5:$D$64,5,$E$5:$E$64,1) | O5: =COUNTIFS($D$5:$D$64,5,$E$5:$E$64,2) | P5: =COUNTIFS($D$5:$D$64,5,$E$5:$E$64,3) | Q5: =COUNTIFS($D$5:$D$64,5,$E$5:$E$64,4) | R5: =COUNTIFS($D$5:$D$64,5,$E$5:$E$64,5)
A6: 2 | B6: SOBRECOSTO EN CIERRE DE OBRA QUERÉTARO | C6: CIERRE DE OBRA QUERÉTARO | D6: 4 | E6: 4 | F6: =IF(OR(D6="",E6=""),"",D6*E6) | G6: =IF(F6="","",IF(F6>=15,"ALTO",IF(F6>=8,"MEDIO","BAJO"))) | H6: PROYECTOS | I6: CONGELAR ALCANCE Y AUTORIZAR CAMBIOS SOLO POR ESCRITO | J6: 46307 | K6: ABIERTO | M6: 4 | N6: =COUNTIFS($D$5:$D$64,4,$E$5:$E$64,1) | O6: =COUNTIFS($D$5:$D$64,4,$E$5:$E$64,2) | P6: =COUNTIFS($D$5:$D$64,4,$E$5:$E$64,3) | Q6: =COUNTIFS($D$5:$D$64,4,$E$5:$E$64,4) | R6: =COUNTIFS($D$5:$D$64,4,$E$5:$E$64,5)
A7: 3 | B7: OBSERVACIONES DEL IMSS POR DIFERENCIAS EN CUOTAS | C7: CUMPLIMIENTO IMSS | D7: 3 | E7: 4 | F7: =IF(OR(D7="",E7=""),"",D7*E7) | G7: =IF(F7="","",IF(F7>=15,"ALTO",IF(F7>=8,"MEDIO","BAJO"))) | H7: RECURSOS HUMANOS | I7: CONCILIAR CÉDULA DE DETERMINACIÓN CONTRA NÓMINA | J7: 46325 | K7: EN MITIGACIÓN | M7: 3 | N7: =COUNTIFS($D$5:$D$64,3,$E$5:$E$64,1) | O7: =COUNTIFS($D$5:$D$64,3,$E$5:$E$64,2) | P7: =COUNTIFS($D$5:$D$64,3,$E$5:$E$64,3) | Q7: =COUNTIFS($D$5:$D$64,3,$E$5:$E$64,4) | R7: =COUNTIFS($D$5:$D$64,3,$E$5:$E$64,5)
A8: 4 | B8: COBRANZA VENCIDA MAYOR A 90 DÍAS | C8: COBRANZA | D8: 3 | E8: 3 | F8: =IF(OR(D8="",E8=""),"",D8*E8) | G8: =IF(F8="","",IF(F8>=15,"ALTO",IF(F8>=8,"MEDIO","BAJO"))) | H8: FINANZAS | I8: PLAN DE PAGOS Y SUSPENSIÓN DE CRÉDITO | J8: 46315 | K8: ABIERTO | M8: 2 | N8: =COUNTIFS($D$5:$D$64,2,$E$5:$E$64,1) | O8: =COUNTIFS($D$5:$D$64,2,$E$5:$E$64,2) | P8: =COUNTIFS($D$5:$D$64,2,$E$5:$E$64,3) | Q8: =COUNTIFS($D$5:$D$64,2,$E$5:$E$64,4) | R8: =COUNTIFS($D$5:$D$64,2,$E$5:$E$64,5)
A9: 5 | B9: ROTACIÓN DE PERSONAL CLAVE EN ADMINISTRACIÓN | C9: ERP ADMINISTRATIVO | D9: 2 | E9: 4 | F9: =IF(OR(D9="",E9=""),"",D9*E9) | G9: =IF(F9="","",IF(F9>=15,"ALTO",IF(F9>=8,"MEDIO","BAJO"))) | H9: RECURSOS HUMANOS | I9: DOCUMENTAR PROCESOS Y CAPACITAR SUPLENTES | J9: 46341 | K9: ABIERTO | M9: 1 | N9: =COUNTIFS($D$5:$D$64,1,$E$5:$E$64,1) | O9: =COUNTIFS($D$5:$D$64,1,$E$5:$E$64,2) | P9: =COUNTIFS($D$5:$D$64,1,$E$5:$E$64,3) | Q9: =COUNTIFS($D$5:$D$64,1,$E$5:$E$64,4) | R9: =COUNTIFS($D$5:$D$64,1,$E$5:$E$64,5)
A10: 6 | B10: FALLA EN EL RESPALDO DE INFORMACIÓN | C10: TECNOLOGÍA | D10: 2 | E10: 5 | F10: =IF(OR(D10="",E10=""),"",D10*E10) | G10: =IF(F10="","",IF(F10>=15,"ALTO",IF(F10>=8,"MEDIO","BAJO"))) | H10: ADMINISTRACIÓN | I10: RESPALDO DIARIO EN NUBE Y PRUEBA MENSUAL DE RESTAURACIÓN | J10: 46320 | K10: ABIERTO
A11: 7 | B11: INFLACIÓN EN MATERIALES DE CONSTRUCCIÓN | C11: NAVE TOLUCA FASE 2 | D11: 3 | E11: 3 | F11: =IF(OR(D11="",E11=""),"",D11*E11) | G11: =IF(F11="","",IF(F11>=15,"ALTO",IF(F11>=8,"MEDIO","BAJO"))) | H11: COMPRAS | I11: CLÁUSULA DE AJUSTE DE PRECIOS EN CONTRATOS | J11: 46327 | K11: ABIERTO
A12: 8 | B12: ERRORES EN TIMBRADO DE FACTURAS | C12: FACTURACIÓN | D12: 2 | E12: 2 | F12: =IF(OR(D12="",E12=""),"",D12*E12) | G12: =IF(F12="","",IF(F12>=15,"ALTO",IF(F12>=8,"MEDIO","BAJO"))) | H12: ADMINISTRACIÓN | I12: VALIDACIÓN PREVIA CON LISTA DE VERIFICACIÓN | J12: 46313 | K12: ABIERTO
A13: 9 | F13: =IF(OR(D13="",E13=""),"",D13*E13) | G13: =IF(F13="","",IF(F13>=15,"ALTO",IF(F13>=8,"MEDIO","BAJO")))
A14: 10 | F14: =IF(OR(D14="",E14=""),"",D14*E14) | G14: =IF(F14="","",IF(F14>=15,"ALTO",IF(F14>=8,"MEDIO","BAJO")))
A15: 11 | F15: =IF(OR(D15="",E15=""),"",D15*E15) | G15: =IF(F15="","",IF(F15>=15,"ALTO",IF(F15>=8,"MEDIO","BAJO")))
A16: 12 | F16: =IF(OR(D16="",E16=""),"",D16*E16) | G16: =IF(F16="","",IF(F16>=15,"ALTO",IF(F16>=8,"MEDIO","BAJO")))
A17: 13 | F17: =IF(OR(D17="",E17=""),"",D17*E17) | G17: =IF(F17="","",IF(F17>=15,"ALTO",IF(F17>=8,"MEDIO","BAJO")))
A18: 14 | F18: =IF(OR(D18="",E18=""),"",D18*E18) | G18: =IF(F18="","",IF(F18>=15,"ALTO",IF(F18>=8,"MEDIO","BAJO")))
A19: 15 | F19: =IF(OR(D19="",E19=""),"",D19*E19) | G19: =IF(F19="","",IF(F19>=15,"ALTO",IF(F19>=8,"MEDIO","BAJO")))
A20: 16 | F20: =IF(OR(D20="",E20=""),"",D20*E20) | G20: =IF(F20="","",IF(F20>=15,"ALTO",IF(F20>=8,"MEDIO","BAJO")))
A21: 17 | F21: =IF(OR(D21="",E21=""),"",D21*E21) | G21: =IF(F21="","",IF(F21>=15,"ALTO",IF(F21>=8,"MEDIO","BAJO")))
A22: 18 | F22: =IF(OR(D22="",E22=""),"",D22*E22) | G22: =IF(F22="","",IF(F22>=15,"ALTO",IF(F22>=8,"MEDIO","BAJO")))
A23: 19 | F23: =IF(OR(D23="",E23=""),"",D23*E23) | G23: =IF(F23="","",IF(F23>=15,"ALTO",IF(F23>=8,"MEDIO","BAJO")))
A24: 20 | F24: =IF(OR(D24="",E24=""),"",D24*E24) | G24: =IF(F24="","",IF(F24>=15,"ALTO",IF(F24>=8,"MEDIO","BAJO")))
... A64: 60 | F64: =IF(OR(D64="",E64=""),"",D64*E64) | G64: =IF(F64="","",IF(F64>=15,"ALTO",IF(F64>=8,"MEDIO","BAJO")))

Sheet DECISIONES
A1: DECISIONES REQUERIDAS A DIRECCIÓN | J1: INSERTE SU LOGO (clic derecho > Insertar imagen)
A2: Contexto, opciones y recomendación para decidir rápido
A4: NO. | B4: DECISIÓN REQUERIDA | C4: CONTEXTO | D4: OPCIONES | E4: RECOMENDACIÓN | F4: QUIÉN DECIDE | G4: FECHA REQUERIDA | H4: ESTATUS | I4: FECHA DE DECISIÓN | J4: DÍAS DE RETRASO | K4: SEMÁFORO
A5: 1 | B5: AUTORIZAR AMPLIACIÓN DE PRESUPUESTO DE CIERRE DE OBRA | C5: SOBRECOSTO DE 4.8% POR OBRA ADICIONAL SOLICITADA POR EL CLIENTE | D5: A) AUTORIZAR $150,000; B) NEGOCIAR COSTO CON CLIENTE; C) ABSORBER | E5: OPCIÓN B CON RESPALDO DE ORDEN DE CAMBIO | F5: DIRECCIÓN | G5: 46301 | H5: PENDIENTE | J5: =IF(OR(B5="",G5="",H5<>"PENDIENTE"),"",MAX(0,FECHA_CORTE-G5)) | K5: =IF(B5="","",IF(H5<>"PENDIENTE","CUMPLIDO",IF(G5="","SIN FECHA",IF(G5<FECHA_CORTE,"VENCIDO",IF(G5-FECHA_CORTE<=2,"POR VENCER","EN TIEMPO")))))
A6: 2 | B6: SELECCIONAR PROVEEDOR DE ACERO ESTRUCTURAL | C6: TRES COTIZACIONES CON DIFERENCIAS DE PRECIO Y TIEMPO DE ENTREGA | D6: A) PROVEEDOR LOCAL; B) IMPORTADO; C) DIVIDIR PEDIDO | E6: OPCIÓN C PARA MITIGAR RETRASO | F6: DIRECCIÓN | G6: 46304 | H6: PENDIENTE | J6: =IF(OR(B6="",G6="",H6<>"PENDIENTE"),"",MAX(0,FECHA_CORTE-G6)) | K6: =IF(B6="","",IF(H6<>"PENDIENTE","CUMPLIDO",IF(G6="","SIN FECHA",IF(G6<FECHA_CORTE,"VENCIDO",IF(G6-FECHA_CORTE<=2,"POR VENCER","EN TIEMPO")))))
A7: 3 | B7: CONTRATAR APOYO TEMPORAL PARA CIERRE FISCAL | C7: CARGA DE TRABAJO DEL CIERRE DE SEPTIEMBRE | D7: A) CONTRATAR; B) HORAS EXTRA | E7: OPCIÓN A POR 4 SEMANAS | F7: DIRECCIÓN | G7: 46298 | H7: APROBADA | J7: =IF(OR(B7="",G7="",H7<>"PENDIENTE"),"",MAX(0,FECHA_CORTE-G7)) | K7: =IF(B7="","",IF(H7<>"PENDIENTE","CUMPLIDO",IF(G7="","SIN FECHA",IF(G7<FECHA_CORTE,"VENCIDO",IF(G7-FECHA_CORTE<=2,"POR VENCER","EN TIEMPO")))))
A8: 4 | B8: CAMBIAR PROCESO DE AUTORIZACIÓN DE COMPRAS MAYORES A $50,000 | C8: COMPRAS SIN SOPORTE COMPLETO | D8: A) DOBLE FIRMA; B) COMITÉ SEMANAL | E8: OPCIÓN A | F8: DIRECCIÓN | G8: 46307 | H8: PENDIENTE | J8: =IF(OR(B8="",G8="",H8<>"PENDIENTE"),"",MAX(0,FECHA_CORTE-G8)) | K8: =IF(B8="","",IF(H8<>"PENDIENTE","CUMPLIDO",IF(G8="","SIN FECHA",IF(G8<FECHA_CORTE,"VENCIDO",IF(G8-FECHA_CORTE<=2,"POR VENCER","EN TIEMPO")))))
A9: 5 | J9: =IF(OR(B9="",G9="",H9<>"PENDIENTE"),"",MAX(0,FECHA_CORTE-G9)) | K9: =IF(B9="","",IF(H9<>"PENDIENTE","CUMPLIDO",IF(G9="","SIN FECHA",IF(G9<FECHA_CORTE,"VENCIDO",IF(G9-FECHA_CORTE<=2,"POR VENCER","EN TIEMPO")))))
A10: 6 | J10: =IF(OR(B10="",G10="",H10<>"PENDIENTE"),"",MAX(0,FECHA_CORTE-G10)) | K10: =IF(B10="","",IF(H10<>"PENDIENTE","CUMPLIDO",IF(G10="","SIN FECHA",IF(G10<FECHA_CORTE,"VENCIDO",IF(G10-FECHA_CORTE<=2,"POR VENCER","EN TIEMPO")))))
A11: 7 | J11: =IF(OR(B11="",G11="",H11<>"PENDIENTE"),"",MAX(0,FECHA_CORTE-G11)) | K11: =IF(B11="","",IF(H11<>"PENDIENTE","CUMPLIDO",IF(G11="","SIN FECHA",IF(G11<FECHA_CORTE,"VENCIDO",IF(G11-FECHA_CORTE<=2,"POR VENCER","EN TIEMPO")))))
A12: 8 | J12: =IF(OR(B12="",G12="",H12<>"PENDIENTE"),"",MAX(0,FECHA_CORTE-G12)) | K12: =IF(B12="","",IF(H12<>"PENDIENTE","CUMPLIDO",IF(G12="","SIN FECHA",IF(G12<FECHA_CORTE,"VENCIDO",IF(G12-FECHA_CORTE<=2,"POR VENCER","EN TIEMPO")))))
A13: 9 | J13: =IF(OR(B13="",G13="",H13<>"PENDIENTE"),"",MAX(0,FECHA_CORTE-G13)) | K13: =IF(B13="","",IF(H13<>"PENDIENTE","CUMPLIDO",IF(G13="","SIN FECHA",IF(G13<FECHA_CORTE,"VENCIDO",IF(G13-FECHA_CORTE<=2,"POR VENCER","EN TIEMPO")))))
A14: 10 | J14: =IF(OR(B14="",G14="",H14<>"PENDIENTE"),"",MAX(0,FECHA_CORTE-G14)) | K14: =IF(B14="","",IF(H14<>"PENDIENTE","CUMPLIDO",IF(G14="","SIN FECHA",IF(G14<FECHA_CORTE,"VENCIDO",IF(G14-FECHA_CORTE<=2,"POR VENCER","EN TIEMPO")))))
A15: 11 | J15: =IF(OR(B15="",G15="",H15<>"PENDIENTE"),"",MAX(0,FECHA_CORTE-G15)) | K15: =IF(B15="","",IF(H15<>"PENDIENTE","CUMPLIDO",IF(G15="","SIN FECHA",IF(G15<FECHA_CORTE,"VENCIDO",IF(G15-FECHA_CORTE<=2,"POR VENCER","EN TIEMPO")))))
A16: 12 | J16: =IF(OR(B16="",G16="",H16<>"PENDIENTE"),"",MAX(0,FECHA_CORTE-G16)) | K16: =IF(B16="","",IF(H16<>"PENDIENTE","CUMPLIDO",IF(G16="","SIN FECHA",IF(G16<FECHA_CORTE,"VENCIDO",IF(G16-FECHA_CORTE<=2,"POR VENCER","EN TIEMPO")))))
A17: 13 | J17: =IF(OR(B17="",G17="",H17<>"PENDIENTE"),"",MAX(0,FECHA_CORTE-G17)) | K17: =IF(B17="","",IF(H17<>"PENDIENTE","CUMPLIDO",IF(G17="","SIN FECHA",IF(G17<FECHA_CORTE,"VENCIDO",IF(G17-FECHA_CORTE<=2,"POR VENCER","EN TIEMPO")))))
A18: 14 | J18: =IF(OR(B18="",G18="",H18<>"PENDIENTE"),"",MAX(0,FECHA_CORTE-G18)) | K18: =IF(B18="","",IF(H18<>"PENDIENTE","CUMPLIDO",IF(G18="","SIN FECHA",IF(G18<FECHA_CORTE,"VENCIDO",IF(G18-FECHA_CORTE<=2,"POR VENCER","EN TIEMPO")))))
A19: 15 | J19: =IF(OR(B19="",G19="",H19<>"PENDIENTE"),"",MAX(0,FECHA_CORTE-G19)) | K19: =IF(B19="","",IF(H19<>"PENDIENTE","CUMPLIDO",IF(G19="","SIN FECHA",IF(G19<FECHA_CORTE,"VENCIDO",IF(G19-FECHA_CORTE<=2,"POR VENCER","EN TIEMPO")))))
A20: 16 | J20: =IF(OR(B20="",G20="",H20<>"PENDIENTE"),"",MAX(0,FECHA_CORTE-G20)) | K20: =IF(B20="","",IF(H20<>"PENDIENTE","CUMPLIDO",IF(G20="","SIN FECHA",IF(G20<FECHA_CORTE,"VENCIDO",IF(G20-FECHA_CORTE<=2,"POR VENCER","EN TIEMPO")))))
... A64: 60 | J64: =IF(OR(B64="",G64="",H64<>"PENDIENTE"),"",MAX(0,FECHA_CORTE-G64)) | K64: =IF(B64="","",IF(H64<>"PENDIENTE","CUMPLIDO",IF(G64="","SIN FECHA",IF(G64<FECHA_CORTE,"VENCIDO",IF(G64-FECHA_CORTE<=2,"POR VENCER","EN TIEMPO")))))

Sheet INDICADORES
A1: INDICADORES OPERATIVOS | S1: INSERTE SU LOGO (clic derecho > Insertar imagen)
A2: Meta, 12 semanas de historia, cumplimiento y semáforo
A4: NO. | B4: INDICADOR | C4: UNIDAD | D4: SENTIDO | E4: META | F4: S1 | G4: S2 | H4: S3 | I4: S4 | J4: S5 | K4: S6 | L4: S7 | M4: S8 | N4: S9 | O4: S10 | P4: S11 | Q4: S12 | R4: ÚLTIMO VALOR | S4: CUMPLIMIENTO | T4: SEMÁFORO
A5: 1 | B5: % DE ACTIVIDADES CUMPLIDAS EN TIEMPO | C5: % | D5: MAYOR ES MEJOR | E5: 90 | F5: 78 | G5: 82 | H5: 85 | I5: 84 | J5: 88 | K5: 86 | R5: =IFERROR(LOOKUP(2,1/(F5:Q5<>""),F5:Q5),"") | S5: =IF(OR(E5="",R5=""),"",IF(D5="MENOR ES MEJOR",IF(R5=0,1,E5/R5),IF(E5=0,"",R5/E5))) | T5: =IF(S5="","",IF(S5>=1,"EN META",IF(S5>=0.9,"EN RIESGO","FUERA DE META")))
A6: 2 | B6: FACTURACIÓN SEMANAL | C6: MXN | D6: MAYOR ES MEJOR | E6: 300000 | F6: 255000 | G6: 280000 | H6: 310000 | I6: 295000 | J6: 330000 | K6: 318000 | R6: =IFERROR(LOOKUP(2,1/(F6:Q6<>""),F6:Q6),"") | S6: =IF(OR(E6="",R6=""),"",IF(D6="MENOR ES MEJOR",IF(R6=0,1,E6/R6),IF(E6=0,"",R6/E6))) | T6: =IF(S6="","",IF(S6>=1,"EN META",IF(S6>=0.9,"EN RIESGO","FUERA DE META")))
A7: 3 | B7: COBRANZA SEMANAL | C7: MXN | D7: MAYOR ES MEJOR | E7: 280000 | F7: 190000 | G7: 210000 | H7: 240000 | I7: 255000 | J7: 262000 | K7: 270000 | R7: =IFERROR(LOOKUP(2,1/(F7:Q7<>""),F7:Q7),"") | S7: =IF(OR(E7="",R7=""),"",IF(D7="MENOR ES MEJOR",IF(R7=0,1,E7/R7),IF(E7=0,"",R7/E7))) | T7: =IF(S7="","",IF(S7>=1,"EN META",IF(S7>=0.9,"EN RIESGO","FUERA DE META")))
A8: 4 | B8: DÍAS PROMEDIO DE COBRO | C8: DÍAS | D8: MENOR ES MEJOR | E8: 35 | F8: 48 | G8: 46 | H8: 44 | I8: 43 | J8: 41 | K8: 40 | R8: =IFERROR(LOOKUP(2,1/(F8:Q8<>""),F8:Q8),"") | S8: =IF(OR(E8="",R8=""),"",IF(D8="MENOR ES MEJOR",IF(R8=0,1,E8/R8),IF(E8=0,"",R8/E8))) | T8: =IF(S8="","",IF(S8>=1,"EN META",IF(S8>=0.9,"EN RIESGO","FUERA DE META")))
A9: 5 | B9: COMPRAS AUTORIZADAS EN TIEMPO | C9: % | D9: MAYOR ES MEJOR | E9: 95 | F9: 88 | G9: 90 | H9: 92 | I9: 91 | J9: 94 | K9: 96 | R9: =IFERROR(LOOKUP(2,1/(F9:Q9<>""),F9:Q9),"") | S9: =IF(OR(E9="",R9=""),"",IF(D9="MENOR ES MEJOR",IF(R9=0,1,E9/R9),IF(E9=0,"",R9/E9))) | T9: =IF(S9="","",IF(S9>=1,"EN META",IF(S9>=0.9,"EN RIESGO","FUERA DE META")))
A10: 6 | B10: INCIDENCIAS DE NÓMINA | C10: CASOS | D10: MENOR ES MEJOR | E10: 3 | F10: 7 | G10: 6 | H10: 5 | I10: 5 | J10: 4 | K10: 3 | R10: =IFERROR(LOOKUP(2,1/(F10:Q10<>""),F10:Q10),"") | S10: =IF(OR(E10="",R10=""),"",IF(D10="MENOR ES MEJOR",IF(R10=0,1,E10/R10),IF(E10=0,"",R10/E10))) | T10: =IF(S10="","",IF(S10>=1,"EN META",IF(S10>=0.9,"EN RIESGO","FUERA DE META")))
A11: 7 | B11: PENDIENTES VENCIDOS | C11: CASOS | D11: MENOR ES MEJOR | E11: 5 | F11: 12 | G11: 11 | H11: 9 | I11: 8 | J11: 7 | K11: 6 | R11: =IFERROR(LOOKUP(2,1/(F11:Q11<>""),F11:Q11),"") | S11: =IF(OR(E11="",R11=""),"",IF(D11="MENOR ES MEJOR",IF(R11=0,1,E11/R11),IF(E11=0,"",R11/E11))) | T11: =IF(S11="","",IF(S11>=1,"EN META",IF(S11>=0.9,"EN RIESGO","FUERA DE META")))
A12: 8 | B12: AVANCE PROMEDIO DE PROYECTOS | C12: % | D12: MAYOR ES MEJOR | E12: 60 | F12: 38 | G12: 41 | H12: 44 | I12: 46 | J12: 49 | K12: 52 | R12: =IFERROR(LOOKUP(2,1/(F12:Q12<>""),F12:Q12),"") | S12: =IF(OR(E12="",R12=""),"",IF(D12="MENOR ES MEJOR",IF(R12=0,1,E12/R12),IF(E12=0,"",R12/E12))) | T12: =IF(S12="","",IF(S12>=1,"EN META",IF(S12>=0.9,"EN RIESGO","FUERA DE META")))
A13: 9 | R13: =IFERROR(LOOKUP(2,1/(F13:Q13<>""),F13:Q13),"") | S13: =IF(OR(E13="",R13=""),"",IF(D13="MENOR ES MEJOR",IF(R13=0,1,E13/R13),IF(E13=0,"",R13/E13))) | T13: =IF(S13="","",IF(S13>=1,"EN META",IF(S13>=0.9,"EN RIESGO","FUERA DE META")))
A14: 10 | R14: =IFERROR(LOOKUP(2,1/(F14:Q14<>""),F14:Q14),"") | S14: =IF(OR(E14="",R14=""),"",IF(D14="MENOR ES MEJOR",IF(R14=0,1,E14/R14),IF(E14=0,"",R14/E14))) | T14: =IF(S14="","",IF(S14>=1,"EN META",IF(S14>=0.9,"EN RIESGO","FUERA DE META")))
A15: 11 | R15: =IFERROR(LOOKUP(2,1/(F15:Q15<>""),F15:Q15),"") | S15: =IF(OR(E15="",R15=""),"",IF(D15="MENOR ES MEJOR",IF(R15=0,1,E15/R15),IF(E15=0,"",R15/E15))) | T15: =IF(S15="","",IF(S15>=1,"EN META",IF(S15>=0.9,"EN RIESGO","FUERA DE META")))
A16: 12 | R16: =IFERROR(LOOKUP(2,1/(F16:Q16<>""),F16:Q16),"") | S16: =IF(OR(E16="",R16=""),"",IF(D16="MENOR ES MEJOR",IF(R16=0,1,E16/R16),IF(E16=0,"",R16/E16))) | T16: =IF(S16="","",IF(S16>=1,"EN META",IF(S16>=0.9,"EN RIESGO","FUERA DE META")))
A17: 13 | R17: =IFERROR(LOOKUP(2,1/(F17:Q17<>""),F17:Q17),"") | S17: =IF(OR(E17="",R17=""),"",IF(D17="MENOR ES MEJOR",IF(R17=0,1,E17/R17),IF(E17=0,"",R17/E17))) | T17: =IF(S17="","",IF(S17>=1,"EN META",IF(S17>=0.9,"EN RIESGO","FUERA DE META")))
A18: 14 | R18: =IFERROR(LOOKUP(2,1/(F18:Q18<>""),F18:Q18),"") | S18: =IF(OR(E18="",R18=""),"",IF(D18="MENOR ES MEJOR",IF(R18=0,1,E18/R18),IF(E18=0,"",R18/E18))) | T18: =IF(S18="","",IF(S18>=1,"EN META",IF(S18>=0.9,"EN RIESGO","FUERA DE META")))
A19: 15 | R19: =IFERROR(LOOKUP(2,1/(F19:Q19<>""),F19:Q19),"") | S19: =IF(OR(E19="",R19=""),"",IF(D19="MENOR ES MEJOR",IF(R19=0,1,E19/R19),IF(E19=0,"",R19/E19))) | T19: =IF(S19="","",IF(S19>=1,"EN META",IF(S19>=0.9,"EN RIESGO","FUERA DE META")))
A20: 16 | R20: =IFERROR(LOOKUP(2,1/(F20:Q20<>""),F20:Q20),"") | S20: =IF(OR(E20="",R20=""),"",IF(D20="MENOR ES MEJOR",IF(R20=0,1,E20/R20),IF(E20=0,"",R20/E20))) | T20: =IF(S20="","",IF(S20>=1,"EN META",IF(S20>=0.9,"EN RIESGO","FUERA DE META")))
A21: 17 | R21: =IFERROR(LOOKUP(2,1/(F21:Q21<>""),F21:Q21),"") | S21: =IF(OR(E21="",R21=""),"",IF(D21="MENOR ES MEJOR",IF(R21=0,1,E21/R21),IF(E21=0,"",R21/E21))) | T21: =IF(S21="","",IF(S21>=1,"EN META",IF(S21>=0.9,"EN RIESGO","FUERA DE META")))
A22: 18 | R22: =IFERROR(LOOKUP(2,1/(F22:Q22<>""),F22:Q22),"") | S22: =IF(OR(E22="",R22=""),"",IF(D22="MENOR ES MEJOR",IF(R22=0,1,E22/R22),IF(E22=0,"",R22/E22))) | T22: =IF(S22="","",IF(S22>=1,"EN META",IF(S22>=0.9,"EN RIESGO","FUERA DE META")))
A23: 19 | R23: =IFERROR(LOOKUP(2,1/(F23:Q23<>""),F23:Q23),"") | S23: =IF(OR(E23="",R23=""),"",IF(D23="MENOR ES MEJOR",IF(R23=0,1,E23/R23),IF(E23=0,"",R23/E23))) | T23: =IF(S23="","",IF(S23>=1,"EN META",IF(S23>=0.9,"EN RIESGO","FUERA DE META")))
A24: 20 | R24: =IFERROR(LOOKUP(2,1/(F24:Q24<>""),F24:Q24),"") | S24: =IF(OR(E24="",R24=""),"",IF(D24="MENOR ES MEJOR",IF(R24=0,1,E24/R24),IF(E24=0,"",R24/E24))) | T24: =IF(S24="","",IF(S24>=1,"EN META",IF(S24>=0.9,"EN RIESGO","FUERA DE META")))

Sheet CATÁLOGOS
A1: CATÁLOGOS EDITABLES | G1: INSERTE SU LOGO (clic derecho > Insertar imagen)
A2: Las listas desplegables del formato se alimentan de estas columnas
B4: RESPONSABLES | C4: ESTATUS | D4: PRIORIDAD | E4: ESTATUS DE DECISIÓN | F4: ESCALA 1 A 5 | G4: SENTIDO DEL INDICADOR
B5: ADMINISTRACIÓN | C5: PENDIENTE | D5: ALTA | E5: PENDIENTE | F5: 1 | G5: MAYOR ES MEJOR
B6: COMPRAS | C6: EN PROCESO | D6: MEDIA | E6: APROBADA | F6: 2 | G6: MENOR ES MEJOR
B7: FINANZAS | C7: TERMINADO | D7: BAJA | E7: RECHAZADA | F7: 3
B8: RECURSOS HUMANOS | C8: BLOQUEADO | E8: APLAZADA | F8: 4
B9: OPERACIONES | F9: 5
B10: PROYECTOS
B11: VENTAS
B12: DIRECCIÓN
B36: Escribe una opción por renglón, sin dejar espacios en blanco entre ellas.

Sheet AYUDA
B1: AYUDA Y PREGUNTAS FRECUENTES
B2: CONTROL OPERATIVO SEMANAL
B5: PREGUNTAS FRECUENTES
C6: ¿Cómo funcionan los semáforos? | D6: En actividades, pendientes y decisiones: VENCIDO si la fecha compromiso ya pasó, POR VENCER si faltan 2 días o menos, EN TIEMPO en el resto y CUMPLIDO si está terminado. En proyectos y riesgos se calculan con las reglas explicadas en la hoja de cada uno.
C7: ¿Cómo se calcula el avance planeado de un proyecto? | D7: De forma lineal entre la fecha de inicio y la fecha fin planeada, comparada contra la fecha de corte.
C8: ¿Dónde veo el resumen para mi reporte semanal? | D8: En la hoja TABLERO hay un texto automático que puedes copiar al reporte semanal para directivos (Word).
C9: ¿Cuántos renglones puedo capturar? | D9: 200 actividades, 40 proyectos, 150 pendientes, 60 riesgos, 60 decisiones y 20 indicadores con 12 semanas de historia.
C10: ¿Por qué no puedo escribir en algunas celdas? | D10: La hoja está protegida para que no se borren fórmulas por accidente. Solo se editan las celdas de captura (color crema). Si necesitas modificar algo más: pestaña Revisar > Desproteger hoja (no tiene contraseña).
C11: ¿Cómo agrego mi logotipo? | D11: Haz clic en el recuadro punteado de la esquina superior derecha del formato y usa Insertar > Imágenes. Ajusta el tamaño sin salirte del recuadro.
C12: ¿Cómo lo imprimo o lo convierto a PDF? | D12: Archivo > Imprimir (ya está ajustado a una hoja de ancho). Para PDF elige 'Microsoft Print to PDF' o Archivo > Exportar > PDF.
C13: ¿Con qué versiones de Excel funciona? | D13: Excel 2016, 2019, 2021 y Microsoft 365 (Windows y Mac). Funciona en LibreOffice y Google Sheets, aunque algunas gráficas y formatos pueden verse distintos.
C14: ¿Por qué la letra se ve diferente? | D14: El diseño usa la fuente Abadi, incluida en Microsoft 365. Si tu versión no la tiene, Excel la sustituye por otra; no afecta el funcionamiento.
C15: ¿Puedo usarlo en varias empresas o por varios años? | D15: Sí. Guarda una copia del archivo por empresa o por periodo (Archivo > Guardar como) y deja el original en blanco como plantilla maestra.
B17: GLOSARIO
C18: SEMÁFORO | D18: Indicador visual de estado: verde (en control), ámbar (atención) y coral/rojo (acción inmediata).
C19: NIVEL DE RIESGO | D19: Probabilidad x impacto (1 a 25). Alto >= 15, medio 8 a 14, bajo < 8.
C20: AVANCE PLANEADO | D20: Porcentaje que debería llevar el proyecto según calendario.
C21: DESVIACIÓN | D21: Avance real - avance planeado.
C22: CUMPLIMIENTO | D22: Resultado real / meta del indicador.
B24: LISTA DE VERIFICACIÓN (marca ☑ al completar)
B25: ☐ | C25: Fecha de corte actualizada
B26: ☐ | C26: Actividades de la semana capturadas y con estatus
B27: ☐ | C27: Pendientes con responsable y fecha
B28: ☐ | C28: Riesgos nuevos evaluados
B29: ☐ | C29: Decisiones requeridas listas para la junta
B30: ☐ | C30: Indicadores de la semana capturados
B31: ☐ | C31: Reporte semanal enviado
