Workbook

Sheet Formato
A1: CONTROL DE ACTIVOS FIJOS Y DEPRECIACIÓN | K1: INSERTE SU LOGO (clic derecho > Insertar imagen)
A2: Depreciación en línea recta con tasas máximas de la LISR como referencia
A4: Empresa | F4: Fecha de corte | G4: =TODAY()
A6: No. | B6: Código | C6: Descripción | D6: Categoría | E6: Fecha adquisición | F6: Costo (MOI) | G6: Tasa anual | H6: Dep. anual | I6: Años en uso | J6: Dep. acumulada | K6: Valor en libros | L6: Ubicación / Responsable
A7: 1 | G7: =IF(D7="","",IFERROR(VLOOKUP(D7,Tasas!$A$2:$B$10,2,FALSE),0)) | H7: =IF(F7="","",F7*G7) | I7: =IF(E7="","",MAX(0,($G$4-E7)/365)) | J7: =IF(F7="","",MIN(F7,H7*I7)) | K7: =IF(F7="","",F7-J7)
A8: 2 | G8: =IF(D8="","",IFERROR(VLOOKUP(D8,Tasas!$A$2:$B$10,2,FALSE),0)) | H8: =IF(F8="","",F8*G8) | I8: =IF(E8="","",MAX(0,($G$4-E8)/365)) | J8: =IF(F8="","",MIN(F8,H8*I8)) | K8: =IF(F8="","",F8-J8)
A9: 3 | G9: =IF(D9="","",IFERROR(VLOOKUP(D9,Tasas!$A$2:$B$10,2,FALSE),0)) | H9: =IF(F9="","",F9*G9) | I9: =IF(E9="","",MAX(0,($G$4-E9)/365)) | J9: =IF(F9="","",MIN(F9,H9*I9)) | K9: =IF(F9="","",F9-J9)
A10: 4 | G10: =IF(D10="","",IFERROR(VLOOKUP(D10,Tasas!$A$2:$B$10,2,FALSE),0)) | H10: =IF(F10="","",F10*G10) | I10: =IF(E10="","",MAX(0,($G$4-E10)/365)) | J10: =IF(F10="","",MIN(F10,H10*I10)) | K10: =IF(F10="","",F10-J10)
A11: 5 | G11: =IF(D11="","",IFERROR(VLOOKUP(D11,Tasas!$A$2:$B$10,2,FALSE),0)) | H11: =IF(F11="","",F11*G11) | I11: =IF(E11="","",MAX(0,($G$4-E11)/365)) | J11: =IF(F11="","",MIN(F11,H11*I11)) | K11: =IF(F11="","",F11-J11)
A12: 6 | G12: =IF(D12="","",IFERROR(VLOOKUP(D12,Tasas!$A$2:$B$10,2,FALSE),0)) | H12: =IF(F12="","",F12*G12) | I12: =IF(E12="","",MAX(0,($G$4-E12)/365)) | J12: =IF(F12="","",MIN(F12,H12*I12)) | K12: =IF(F12="","",F12-J12)
A13: 7 | G13: =IF(D13="","",IFERROR(VLOOKUP(D13,Tasas!$A$2:$B$10,2,FALSE),0)) | H13: =IF(F13="","",F13*G13) | I13: =IF(E13="","",MAX(0,($G$4-E13)/365)) | J13: =IF(F13="","",MIN(F13,H13*I13)) | K13: =IF(F13="","",F13-J13)
A14: 8 | G14: =IF(D14="","",IFERROR(VLOOKUP(D14,Tasas!$A$2:$B$10,2,FALSE),0)) | H14: =IF(F14="","",F14*G14) | I14: =IF(E14="","",MAX(0,($G$4-E14)/365)) | J14: =IF(F14="","",MIN(F14,H14*I14)) | K14: =IF(F14="","",F14-J14)
A15: 9 | G15: =IF(D15="","",IFERROR(VLOOKUP(D15,Tasas!$A$2:$B$10,2,FALSE),0)) | H15: =IF(F15="","",F15*G15) | I15: =IF(E15="","",MAX(0,($G$4-E15)/365)) | J15: =IF(F15="","",MIN(F15,H15*I15)) | K15: =IF(F15="","",F15-J15)
A16: 10 | G16: =IF(D16="","",IFERROR(VLOOKUP(D16,Tasas!$A$2:$B$10,2,FALSE),0)) | H16: =IF(F16="","",F16*G16) | I16: =IF(E16="","",MAX(0,($G$4-E16)/365)) | J16: =IF(F16="","",MIN(F16,H16*I16)) | K16: =IF(F16="","",F16-J16)
A17: 11 | G17: =IF(D17="","",IFERROR(VLOOKUP(D17,Tasas!$A$2:$B$10,2,FALSE),0)) | H17: =IF(F17="","",F17*G17) | I17: =IF(E17="","",MAX(0,($G$4-E17)/365)) | J17: =IF(F17="","",MIN(F17,H17*I17)) | K17: =IF(F17="","",F17-J17)
A18: 12 | G18: =IF(D18="","",IFERROR(VLOOKUP(D18,Tasas!$A$2:$B$10,2,FALSE),0)) | H18: =IF(F18="","",F18*G18) | I18: =IF(E18="","",MAX(0,($G$4-E18)/365)) | J18: =IF(F18="","",MIN(F18,H18*I18)) | K18: =IF(F18="","",F18-J18)
... A56: 50 | G56: =IF(D56="","",IFERROR(VLOOKUP(D56,Tasas!$A$2:$B$10,2,FALSE),0)) | H56: =IF(F56="","",F56*G56) | I56: =IF(E56="","",MAX(0,($G$4-E56)/365)) | J56: =IF(F56="","",MIN(F56,H56*I56)) | K56: =IF(F56="","",F56-J56)
E57: TOTAL | F57: =SUM(F7:F56) | H57: =SUM(H7:H56) | J57: =SUM(J7:J56) | K57: =SUM(K7:K56)

Sheet Tasas
A1: Categoría | B1: Tasa anual (ref.)
A2: Mobiliario y equipo de oficina | B2: 0.1
A3: Equipo de cómputo | B3: 0.3
A4: Automóviles | B4: 0.25
A5: Maquinaria y equipo | B5: 0.1
A6: Equipo de comunicación | B6: 0.1
A7: Edificios | B7: 0.05
A8: Herramientas | B8: 0.35
A9: Otros | B9: 0.1

Sheet Instrucciones
B1: Activos fijos
B2: Guía de uso
A4: 1 | B4: Registra cada activo con fecha de adquisición, costo (sin IVA) y categoría.
A5: 2 | B5: La tasa se toma de la hoja 'Tasas' (referencia de porcentajes máximos de la LISR); edítala según tu criterio contable.
A6: 3 | B6: Depreciación acumulada = depreciación anual x años en uso, sin exceder el costo.
A7: 4 | B7: Es una herramienta de control administrativo; consulta a tu contador para efectos fiscales.
A8: 5 | B8: Personaliza: en el recuadro punteado de la esquina superior derecha inserta tu logo (Insertar > Imágenes) y captura los datos de tu empresa en las celdas amarillas.
B10: Celdas amarillas = captura · Celdas grises = cálculo automático (no modificar).
