Workbook

Sheet PORTADA
B2: FORMATOS ADMINISTRATIVOS | E2: VERSIÓN 2.0 · MÉXICO
B4: NÓMINA SIMPLIFICADA
B6: Formato administrativo profesional · editable · listo para imprimir
C9: FÓRMULAS AUTOMÁTICAS | D9: LISTAS DESPLEGABLES | E9: HOJAS PROTEGIDAS | F9: LISTO PARA IMPRIMIR
B15: ¿QUÉ INCLUYE ESTE ARCHIVO?
B16: ▸ | C16: FORMATO | D16: Hoja principal de captura. Aquí registras tu información; las celdas grises calculan solas.
B17: ▸ | C17: RESUMEN | D17: Tablero con indicadores y gráficas que se actualizan automáticamente con tus datos.
B18: ▸ | C18: AYUDA | D18: Preguntas frecuentes, glosario y lista de verificación para cerrar tu periodo.
B20: FICHA TÉCNICA
C21: Capacidad | D21: 60 empleados
C22: Compatibilidad | D22: Excel 2016, 2019, 2021 y Microsoft 365 (Windows y Mac)
C23: Idioma y moneda | D23: Español (México) · Pesos mexicanos (MXN) · IVA 16%
C24: Protección | D24: Hojas protegidas sin contraseña (Revisar > Desproteger hoja)
C25: Fuente | D25: Arial (disponible en Windows, Mac y Google Sheets)
B27: CÓMO USARLO
B28: 1 | C28: Captura sueldo diario, días trabajados y horas extra de cada empleado.
B29: 2 | C29: Las horas extra se pagan al doble de la hora ordinaria (jornada de 8 h).
B30: 3 | C30: El ISR retenido se captura manualmente según la tabla del SAT vigente.
B31: 4 | C31: Ajusta el % de retención IMSS según tu cálculo; el valor incluido es solo una referencia.
B32: 5 | C32: Este formato es de control administrativo. Para timbrado de recibos usa tu sistema de nómina CFDI.
B33: 6 | C33: Personaliza: inserta tu logotipo en el recuadro punteado de la esquina superior derecha (Insertar > Imágenes) y captura los datos de tu empresa en las celdas de captura.
B35: RECOMENDACIONES DE USO
B36: ✓ | C36: Este formato sirve para control interno y estimaciones; el cálculo oficial debe hacerse con tablas vigentes del SAT e IMSS.
B37: ✓ | C37: Captura el ISR retenido que te arroje tu sistema de nómina o tu contador.
B38: ✓ | C38: Las horas extra dobles tienen un límite semanal; verifica la LFT antes de pagar.
B39: ✓ | C39: Guarda un archivo por periodo (semana, quincena o mes).
B41: LEYENDA DE COLORES
C42: CELDA DE CAPTURA: escribe aquí.
C43: CÁLCULO AUTOMÁTICO: no la modifiques.
C44: ENCABEZADOS Y TÍTULOS.
C45: * CAMPO OBLIGATORIO: complétalo antes de imprimir o enviar.
B47: Formatos administrativos · Para uso interno de tu empresa

Sheet FORMATO
A1: NÓMINA SIMPLIFICADA | J1: INSERTE SU LOGO (clic derecho > Insertar imagen)
A2: Cálculo estimado por periodo (referencia administrativa, no sustituye cálculo fiscal)
A4: EMPRESA * | F4: PERIODO *
A5: DÍAS DEL PERIODO | B5: 15 | F5: % RETENCIÓN IMSS (EST.) | G5: 0.0275
A7: NO. | B7: EMPLEADO | C7: SUELDO DIARIO | D7: DÍAS TRAB. | E7: HORAS EXTRA | F7: SUELDO | G7: PAGO HORAS EXTRA | H7: BONOS / OTROS | I7: RETENCIÓN IMSS | J7: ISR RETENIDO | K7: NETO A PAGAR
A8: 1 | F8: =IF(C8="","",C8*D8) | G8: =IF(C8="","",E8*(C8/8)*2) | I8: =IF(C8="","",ROUND((F8+G8)*$G$5,2)) | K8: =IF(C8="","",F8+G8+H8-I8-J8)
A9: 2 | F9: =IF(C9="","",C9*D9) | G9: =IF(C9="","",E9*(C9/8)*2) | I9: =IF(C9="","",ROUND((F9+G9)*$G$5,2)) | K9: =IF(C9="","",F9+G9+H9-I9-J9)
A10: 3 | F10: =IF(C10="","",C10*D10) | G10: =IF(C10="","",E10*(C10/8)*2) | I10: =IF(C10="","",ROUND((F10+G10)*$G$5,2)) | K10: =IF(C10="","",F10+G10+H10-I10-J10)
A11: 4 | F11: =IF(C11="","",C11*D11) | G11: =IF(C11="","",E11*(C11/8)*2) | I11: =IF(C11="","",ROUND((F11+G11)*$G$5,2)) | K11: =IF(C11="","",F11+G11+H11-I11-J11)
A12: 5 | F12: =IF(C12="","",C12*D12) | G12: =IF(C12="","",E12*(C12/8)*2) | I12: =IF(C12="","",ROUND((F12+G12)*$G$5,2)) | K12: =IF(C12="","",F12+G12+H12-I12-J12)
A13: 6 | F13: =IF(C13="","",C13*D13) | G13: =IF(C13="","",E13*(C13/8)*2) | I13: =IF(C13="","",ROUND((F13+G13)*$G$5,2)) | K13: =IF(C13="","",F13+G13+H13-I13-J13)
A14: 7 | F14: =IF(C14="","",C14*D14) | G14: =IF(C14="","",E14*(C14/8)*2) | I14: =IF(C14="","",ROUND((F14+G14)*$G$5,2)) | K14: =IF(C14="","",F14+G14+H14-I14-J14)
A15: 8 | F15: =IF(C15="","",C15*D15) | G15: =IF(C15="","",E15*(C15/8)*2) | I15: =IF(C15="","",ROUND((F15+G15)*$G$5,2)) | K15: =IF(C15="","",F15+G15+H15-I15-J15)
A16: 9 | F16: =IF(C16="","",C16*D16) | G16: =IF(C16="","",E16*(C16/8)*2) | I16: =IF(C16="","",ROUND((F16+G16)*$G$5,2)) | K16: =IF(C16="","",F16+G16+H16-I16-J16)
A17: 10 | F17: =IF(C17="","",C17*D17) | G17: =IF(C17="","",E17*(C17/8)*2) | I17: =IF(C17="","",ROUND((F17+G17)*$G$5,2)) | K17: =IF(C17="","",F17+G17+H17-I17-J17)
A18: 11 | F18: =IF(C18="","",C18*D18) | G18: =IF(C18="","",E18*(C18/8)*2) | I18: =IF(C18="","",ROUND((F18+G18)*$G$5,2)) | K18: =IF(C18="","",F18+G18+H18-I18-J18)
A19: 12 | F19: =IF(C19="","",C19*D19) | G19: =IF(C19="","",E19*(C19/8)*2) | I19: =IF(C19="","",ROUND((F19+G19)*$G$5,2)) | K19: =IF(C19="","",F19+G19+H19-I19-J19)
... A67: 60 | F67: =IF(C67="","",C67*D67) | G67: =IF(C67="","",E67*(C67/8)*2) | I67: =IF(C67="","",ROUND((F67+G67)*$G$5,2)) | K67: =IF(C67="","",F67+G67+H67-I67-J67)
E68: TOTAL | F68: =SUM(F8:F67) | G68: =SUM(G8:G67) | H68: =SUM(H8:H67) | I68: =SUM(I8:I67) | J68: =SUM(J8:J67) | K68: =SUM(K8:K67)
A72: ELABORÓ | D72: REVISÓ | G72: AUTORIZÓ

Sheet RESUMEN
A1: RESUMEN DE NÓMINA | H1: INSERTE SU LOGO (clic derecho > Insertar imagen)
A2: Percepciones, deducciones y neto del periodo
B4: PERCEPCIONES | D4: DEDUCCIONES | F4: NETO A PAGAR | H4: EMPLEADOS
B5: =FORMATO!F68+FORMATO!G68+FORMATO!H68 | D5: =FORMATO!I68+FORMATO!J68 | F5: =FORMATO!K68 | H5: =COUNT(FORMATO!C8:C67)
B7: =IF(H5=0,"Captura empleados en la hoja FORMATO para ver el análisis automático.","Mayor neto: "&INDEX(FORMATO!B8:B67,MATCH(MAX(FORMATO!K8:K67),FORMATO!K8:K67,0))&" ($"&TEXT(MAX(FORMATO!K8:K67),"#,##0")&"). Neto promedio por empleado: $"&TEXT(F5/H5,"#,##0")&".")
B25: EMPLEADO | C25: NETO A PAGAR
B26: =IF(FORMATO!B8="","",FORMATO!B8) | C26: =IF(FORMATO!K8="",0,FORMATO!K8)
B27: =IF(FORMATO!B9="","",FORMATO!B9) | C27: =IF(FORMATO!K9="",0,FORMATO!K9)
B28: =IF(FORMATO!B10="","",FORMATO!B10) | C28: =IF(FORMATO!K10="",0,FORMATO!K10)
B29: =IF(FORMATO!B11="","",FORMATO!B11) | C29: =IF(FORMATO!K11="",0,FORMATO!K11)
B30: =IF(FORMATO!B12="","",FORMATO!B12) | C30: =IF(FORMATO!K12="",0,FORMATO!K12)
B31: =IF(FORMATO!B13="","",FORMATO!B13) | C31: =IF(FORMATO!K13="",0,FORMATO!K13)
B32: =IF(FORMATO!B14="","",FORMATO!B14) | C32: =IF(FORMATO!K14="",0,FORMATO!K14)
B33: =IF(FORMATO!B15="","",FORMATO!B15) | C33: =IF(FORMATO!K15="",0,FORMATO!K15)
B34: =IF(FORMATO!B16="","",FORMATO!B16) | C34: =IF(FORMATO!K16="",0,FORMATO!K16)
B35: =IF(FORMATO!B17="","",FORMATO!B17) | C35: =IF(FORMATO!K17="",0,FORMATO!K17)
B36: =IF(FORMATO!B18="","",FORMATO!B18) | C36: =IF(FORMATO!K18="",0,FORMATO!K18)
B37: =IF(FORMATO!B19="","",FORMATO!B19) | C37: =IF(FORMATO!K19="",0,FORMATO!K19)
... B40: =IF(FORMATO!B22="","",FORMATO!B22) | C40: =IF(FORMATO!K22="",0,FORMATO!K22)

Sheet AYUDA
B1: AYUDA Y PREGUNTAS FRECUENTES
B2: NÓMINA SIMPLIFICADA
B5: PREGUNTAS FRECUENTES
C6: ¿El % de IMSS es exacto? | D6: No. Es una referencia editable; la cuota real varía por ramo, salario base de cotización y prima de riesgo.
C7: ¿Sirve para timbrar recibos? | D7: No. Para recibos CFDI de nómina usa tu sistema de timbrado.
C8: ¿Por qué no puedo escribir en algunas celdas? | D8: La hoja está protegida para que no se borren fórmulas por accidente. Solo se editan las celdas de captura (color crema). Si necesitas modificar algo más: pestaña Revisar > Desproteger hoja (no tiene contraseña).
C9: ¿Cómo agrego mi logotipo? | D9: Haz clic en el recuadro punteado de la esquina superior derecha del formato y usa Insertar > Imágenes. Ajusta el tamaño sin salirte del recuadro.
C10: ¿Cómo lo imprimo o lo convierto a PDF? | D10: Archivo > Imprimir (ya está ajustado a una hoja de ancho). Para PDF elige 'Microsoft Print to PDF' o Archivo > Exportar > PDF.
C11: ¿Con qué versiones de Excel funciona? | D11: Excel 2016, 2019, 2021 y Microsoft 365 (Windows y Mac). Funciona en LibreOffice y Google Sheets, aunque algunas gráficas y formatos pueden verse distintos.
C12: ¿Puedo cambiar la letra? | D12: El diseño usa la fuente Arial, disponible en Windows, Mac y Google Sheets. Si necesitas otra, selecciona todo (Ctrl+E) y cambia la fuente; no afecta el funcionamiento.
C13: ¿Puedo usarlo en varias empresas o por varios años? | D13: Sí. Guarda una copia del archivo por empresa o por periodo (Archivo > Guardar como) y deja el original en blanco como plantilla maestra.
B15: GLOSARIO
C16: SUELDO DIARIO | D16: Pago por día laborado.
C17: SDI | D17: Salario diario integrado, base de cotización al IMSS.
C18: PERCEPCIONES | D18: Sueldos, horas extra, bonos y demás pagos.
C19: DEDUCCIONES | D19: ISR, IMSS y otros descuentos.
C20: NETO | D20: Percepciones - deducciones.
B22: LISTA DE VERIFICACIÓN (marca ☑ al completar)
B23: ☐ | C23: Asistencia del periodo validada
B24: ☐ | C24: Horas extra autorizadas
B25: ☐ | C25: ISR/IMSS calculados
B26: ☐ | C26: Dispersión y recibos entregados
