Workbook

Sheet Portada
B2: GRUPO CANVILLE
B4: Control de ingresos y gastos
B5: Formato administrativo editable · México
B10: CÓMO USARLO
B11: 1 | C11: Captura el saldo inicial del periodo en la celda de captura correspondiente.
B12: 2 | C12: Registra cada movimiento: fecha, concepto, categoría (lista desplegable) y método de pago.
B13: 3 | C13: Escribe el monto en la columna Ingreso o Gasto, nunca en ambas.
B14: 4 | C14: El saldo acumulado y los totales se calculan solos.
B15: 5 | C15: Imprime en horizontal; el formato ya está ajustado a una hoja.
B16: 6 | C16: Personaliza: en el recuadro punteado de la esquina superior derecha inserta tu logo (Insertar > Imágenes) y captura los datos de tu empresa en las celdas de captura.
B18: LEYENDA
C19: Celda de captura: escribe aquí.
C20: Cálculo automático: no la modifiques.
C21: Encabezados y títulos.
B24: GRUPO CANVILLE · Formatos administrativos · v1.0

Sheet Formato
A1: CONTROL DE INGRESOS Y GASTOS | G1: INSERTE SU LOGO (clic derecho > Insertar imagen)
A2: Registro diario de movimientos con saldo acumulado
A4: Empresa | B4: Comercializadora Ejemplo S.A. de C.V. | E4: Periodo | F4: Septiembre 2026
A5: Saldo inicial | B5: 15000
A7: No. | B7: Fecha | C7: Concepto | D7: Categoría | E7: Método de pago | F7: Ingreso | G7: Gasto | H7: Saldo
A8: 1 | B8: 46266 | C8: Venta mostrador | D8: Ventas | E8: Efectivo | F8: 18500 | H8: =IF(AND(F8="",G8=""),"",$B$5+SUM($F$8:F8)-SUM($G$8:G8))
A9: 2 | B9: 46267 | C9: Pago de renta de oficina | D9: Renta | E9: Transferencia | G9: 8500 | H9: =IF(AND(F9="",G9=""),"",$B$5+SUM($F$8:F9)-SUM($G$8:G9))
A10: 3 | B10: 46268 | C10: Servicio de consultoría | D10: Servicios | E10: Transferencia | F10: 12000 | H10: =IF(AND(F10="",G10=""),"",$B$5+SUM($F$8:F10)-SUM($G$8:G10))
A11: 4 | B11: 46270 | C11: Nómina primera quincena | D11: Nómina | E11: Transferencia | G11: 14200 | H11: =IF(AND(F11="",G11=""),"",$B$5+SUM($F$8:F11)-SUM($G$8:G11))
A12: 5 | B12: 46272 | C12: Papelería e insumos | D12: Insumos | E12: Tarjeta | G12: 2350.5 | H12: =IF(AND(F12="",G12=""),"",$B$5+SUM($F$8:F12)-SUM($G$8:G12))
A13: 6 | B13: 46274 | C13: Venta mayoreo | D13: Ventas | E13: Transferencia | F13: 26400 | H13: =IF(AND(F13="",G13=""),"",$B$5+SUM($F$8:F13)-SUM($G$8:G13))
A14: 7 | B14: 46275 | C14: Luz y agua | D14: Servicios (luz/agua/tel) | E14: Efectivo | G14: 1890 | H14: =IF(AND(F14="",G14=""),"",$B$5+SUM($F$8:F14)-SUM($G$8:G14))
A15: 8 | B15: 46277 | C15: Campaña en redes sociales | D15: Publicidad | E15: Tarjeta | G15: 3200 | H15: =IF(AND(F15="",G15=""),"",$B$5+SUM($F$8:F15)-SUM($G$8:G15))
A16: 9 | B16: 46279 | C16: Venta mostrador | D16: Ventas | E16: Efectivo | F16: 15750 | H16: =IF(AND(F16="",G16=""),"",$B$5+SUM($F$8:F16)-SUM($G$8:G16))
A17: 10 | B17: 46280 | C17: Pago de IVA | D17: Impuestos | E17: Transferencia | G17: 6120 | H17: =IF(AND(F17="",G17=""),"",$B$5+SUM($F$8:F17)-SUM($G$8:G17))
A18: 11 | B18: 46282 | C18: Servicio de mantenimiento | D18: Servicios | E18: Transferencia | F18: 9800 | H18: =IF(AND(F18="",G18=""),"",$B$5+SUM($F$8:F18)-SUM($G$8:G18))
A19: 12 | B19: 46284 | C19: Combustible de reparto | D19: Transporte | E19: Tarjeta | G19: 1450 | H19: =IF(AND(F19="",G19=""),"",$B$5+SUM($F$8:F19)-SUM($G$8:G19))
A20: 13 | B20: 46285 | C20: Nómina segunda quincena | D20: Nómina | E20: Transferencia | G20: 14200 | H20: =IF(AND(F20="",G20=""),"",$B$5+SUM($F$8:F20)-SUM($G$8:G20))
A21: 14 | B21: 46288 | C21: Intereses ganados | D21: Otros ingresos | E21: Transferencia | F21: 320 | H21: =IF(AND(F21="",G21=""),"",$B$5+SUM($F$8:F21)-SUM($G$8:G21))
A22: 15 | B22: 46290 | C22: Venta mostrador | D22: Ventas | E22: Efectivo | F22: 21300 | H22: =IF(AND(F22="",G22=""),"",$B$5+SUM($F$8:F22)-SUM($G$8:G22))
A23: 16 | B23: 46293 | C23: Reparaciones menores | D23: Otros gastos | E23: Efectivo | G23: 1180 | H23: =IF(AND(F23="",G23=""),"",$B$5+SUM($F$8:F23)-SUM($G$8:G23))
A24: 17 | H24: =IF(AND(F24="",G24=""),"",$B$5+SUM($F$8:F24)-SUM($G$8:G24))
A25: 18 | H25: =IF(AND(F25="",G25=""),"",$B$5+SUM($F$8:F25)-SUM($G$8:G25))
A26: 19 | H26: =IF(AND(F26="",G26=""),"",$B$5+SUM($F$8:F26)-SUM($G$8:G26))
A27: 20 | H27: =IF(AND(F27="",G27=""),"",$B$5+SUM($F$8:F27)-SUM($G$8:G27))
A28: 21 | H28: =IF(AND(F28="",G28=""),"",$B$5+SUM($F$8:F28)-SUM($G$8:G28))
A29: 22 | H29: =IF(AND(F29="",G29=""),"",$B$5+SUM($F$8:F29)-SUM($G$8:G29))
A30: 23 | H30: =IF(AND(F30="",G30=""),"",$B$5+SUM($F$8:F30)-SUM($G$8:G30))
A31: 24 | H31: =IF(AND(F31="",G31=""),"",$B$5+SUM($F$8:F31)-SUM($G$8:G31))
A32: 25 | H32: =IF(AND(F32="",G32=""),"",$B$5+SUM($F$8:F32)-SUM($G$8:G32))
A33: 26 | H33: =IF(AND(F33="",G33=""),"",$B$5+SUM($F$8:F33)-SUM($G$8:G33))
A34: 27 | H34: =IF(AND(F34="",G34=""),"",$B$5+SUM($F$8:F34)-SUM($G$8:G34))
A35: 28 | H35: =IF(AND(F35="",G35=""),"",$B$5+SUM($F$8:F35)-SUM($G$8:G35))
... A57: 50 | H57: =IF(AND(F57="",G57=""),"",$B$5+SUM($F$8:F57)-SUM($G$8:G57))
E58: TOTAL | F58: =SUM(F8:F57) | G58: =SUM(G8:G57) | H58: =B5+F58-G58

Sheet Resumen
A1: RESUMEN DE INGRESOS Y GASTOS | H1: INSERTE SU LOGO (clic derecho > Insertar imagen)
A2: Se actualiza solo con lo que captures en la hoja Formato
B4: TOTAL INGRESOS | D4: TOTAL GASTOS | F4: SALDO FINAL | H4: MOVIMIENTOS
B5: =Formato!F58 | D5: =Formato!G58 | F5: =Formato!H58 | H5: =SUMPRODUCT(--(((Formato!F8:F57<>"")+(Formato!G8:G57<>""))>0))
B25: Gasto por categoría | C25: Monto | F25: Ingreso por categoría | G25: Monto
B26: Nómina | C26: =SUMIF(Formato!$D$8:$D$57,B26,Formato!$G$8:$G$57) | F26: Ventas | G26: =SUMIF(Formato!$D$8:$D$57,F26,Formato!$F$8:$F$57)
B27: Renta | C27: =SUMIF(Formato!$D$8:$D$57,B27,Formato!$G$8:$G$57) | F27: Servicios | G27: =SUMIF(Formato!$D$8:$D$57,F27,Formato!$F$8:$F$57)
B28: Servicios (luz/agua/tel) | C28: =SUMIF(Formato!$D$8:$D$57,B28,Formato!$G$8:$G$57) | F28: Otros ingresos | G28: =SUMIF(Formato!$D$8:$D$57,F28,Formato!$F$8:$F$57)
B29: Insumos | C29: =SUMIF(Formato!$D$8:$D$57,B29,Formato!$G$8:$G$57)
B30: Impuestos | C30: =SUMIF(Formato!$D$8:$D$57,B30,Formato!$G$8:$G$57)
B31: Publicidad | C31: =SUMIF(Formato!$D$8:$D$57,B31,Formato!$G$8:$G$57)
B32: Transporte | C32: =SUMIF(Formato!$D$8:$D$57,B32,Formato!$G$8:$G$57)
B33: Otros gastos | C33: =SUMIF(Formato!$D$8:$D$57,B33,Formato!$G$8:$G$57)
