Workbook

Sheet PORTADA
B2: FORMATOS ADMINISTRATIVOS | E2: VERSIÓN 2.0 · MÉXICO
B4: CONCILIACIÓN BANCARIA
B6: Formato administrativo profesional · editable · listo para imprimir
C9: FÓRMULAS AUTOMÁTICAS | D9: LISTAS DESPLEGABLES | E9: HOJAS PROTEGIDAS | F9: LISTO PARA IMPRIMIR
B15: ¿QUÉ INCLUYE ESTE ARCHIVO?
B16: ▸ | C16: FORMATO | D16: Hoja principal de captura. Aquí registras tu información; las celdas grises calculan solas.
B17: ▸ | C17: PARTIDAS | D17: Detalle de partidas en tránsito y movimientos pendientes de conciliar.
B18: ▸ | C18: AYUDA | D18: Preguntas frecuentes, glosario y lista de verificación para cerrar tu periodo.
B20: FICHA TÉCNICA
C21: Capacidad | D21: 50 partidas por tipo de movimiento
C22: Compatibilidad | D22: Excel 2016, 2019, 2021 y Microsoft 365 (Windows y Mac)
C23: Idioma y moneda | D23: Español (México) · Pesos mexicanos (MXN) · IVA 16%
C24: Protección | D24: Hojas protegidas sin contraseña (Revisar > Desproteger hoja)
C25: Fuente | D25: Arial (disponible en Windows, Mac y Google Sheets)
B27: CÓMO USARLO
B28: 1 | C28: Captura banco, cuenta, mes y fecha de corte; después el saldo final del estado de cuenta y el saldo de tus libros.
B29: 2 | C29: En la hoja PARTIDAS lista los depósitos y cheques en tránsito (hasta 50 de cada uno) y los movimientos del banco que aún no registras.
B30: 3 | C30: Los totales de las partidas alimentan automáticamente la conciliación: no necesitas sumarlas.
B31: 4 | C31: Captura manualmente solo los errores del banco o de libros y los cheques devueltos, si los hay.
B32: 5 | C32: Cuando la diferencia sea 0 el formato indica CONCILIADO; si no, revisa el detalle de partidas.
B33: 6 | C33: Las partidas con más de 30 días se resaltan para que les des seguimiento.
B34: 7 | C34: Personaliza: inserta tu logotipo en el recuadro punteado de la esquina superior derecha (Insertar > Imágenes) y captura los datos de tu empresa en las celdas de captura.
B36: RECOMENDACIONES DE USO
B37: ✓ | C37: Concilia cada mes con el estado de cuenta del banco, sin importar si hubo pocos movimientos.
B38: ✓ | C38: Captura en PARTIDAS cada depósito y cheque en tránsito; el formato suma solo.
B39: ✓ | C39: Una diferencia distinta de cero casi siempre es una comisión no registrada o un error de captura.
B40: ✓ | C40: Los cheques en tránsito con más de 90 días deben cancelarse o reexpedirse.
B42: LEYENDA DE COLORES
C43: CELDA DE CAPTURA: escribe aquí.
C44: CÁLCULO AUTOMÁTICO: no la modifiques.
C45: ENCABEZADOS Y TÍTULOS.
C46: * CAMPO OBLIGATORIO: complétalo antes de imprimir o enviar.
B48: Formatos administrativos · Para uso interno de tu empresa

Sheet FORMATO
A1: CONCILIACIÓN BANCARIA | D1: INSERTE SU LOGO (clic derecho > Insertar imagen)
A2: Saldo en libros vs. estado de cuenta, con detalle de partidas en tránsito
A4: BANCO * | B4: BBVA
A5: CUENTA * | B5: 0123456789
A6: MES * | B6: SEPTIEMBRE 2026
A7: FECHA DE CORTE | B7: 46295
B9: SEGÚN ESTADO DE CUENTA
B10: SALDO FINAL SEGÚN BANCO | C10: 184250.4
B11: (+) DEPÓSITOS EN TRÁNSITO (HOJA PARTIDAS) | C11: =SUM(PARTIDAS!D5:D54)
B12: (-) CHEQUES Y PAGOS EN TRÁNSITO (HOJA PARTIDAS) | C12: =SUM(PARTIDAS!J5:J54)
B13: (+/-) ERRORES DEL BANCO | C13: 0
B14: SALDO BANCARIO AJUSTADO | C14: =C10+C11-C12+C13
B16: SEGÚN LIBROS
B17: SALDO FINAL SEGÚN LIBROS | C17: 188280.15
B18: (+) ABONOS DEL BANCO NO REGISTRADOS (INTERESES, DEPÓSITOS) | C18: =SUMIF(PARTIDAS!P5:P54,"ABONO",PARTIDAS!Q5:Q54)
B19: (-) CARGOS DEL BANCO NO REGISTRADOS (COMISIONES, IVA) | C19: =SUMIF(PARTIDAS!P5:P54,"CARGO",PARTIDAS!Q5:Q54)
B20: (-) CHEQUES DEVUELTOS | C20: 0
B21: (+/-) ERRORES EN LIBROS | C21: 0
B22: SALDO EN LIBROS AJUSTADO | C22: =C17+C18-C19-C20+C21
B24: DIFERENCIA (DEBE SER 0) | C24: =ROUND(C14-C22,2)
B25: =IF(AND(C10="",C17=""),"",IF(C24=0,"✔ CONCILIADO","✘ REVISAR PARTIDAS PENDIENTES"))
B27: INDICADORES DE CONTROL
B28: PARTIDAS EN TRÁNSITO | C28: =COUNT(PARTIDAS!D5:D54)+COUNT(PARTIDAS!J5:J54)
B29: IMPORTE TOTAL EN TRÁNSITO | C29: =C11+C12
B30: PARTIDAS CON MÁS DE 30 DÍAS | C30: =COUNTIF(PARTIDAS!E5:E54,">30")+COUNTIF(PARTIDAS!K5:K54,">30")
B31: PARTIDAS CON MÁS DE 90 DÍAS (CANCELAR O REEXPEDIR) | C31: =COUNTIF(PARTIDAS!E5:E54,">90")+COUNTIF(PARTIDAS!K5:K54,">90")
A36: ELABORÓ | C36: AUTORIZÓ

Sheet PARTIDAS
A1: PARTIDAS DE CONCILIACIÓN | P1: INSERTE SU LOGO (clic derecho > Insertar imagen)
A2: Depósitos y cheques en tránsito, y movimientos del banco no registrados
A3: DEPÓSITOS EN TRÁNSITO (SUMAN AL BANCO) | G3: CHEQUES Y PAGOS EN TRÁNSITO (RESTAN AL BANCO) | M3: MOVIMIENTOS DEL BANCO NO REGISTRADOS EN LIBROS
A4: NO. | B4: FECHA | C4: DESCRIPCIÓN / REFERENCIA | D4: IMPORTE | E4: DÍAS | G4: NO. | H4: FECHA | I4: NO. CHEQUE / BENEFICIARIO | J4: IMPORTE | K4: DÍAS | M4: NO. | N4: FECHA | O4: DESCRIPCIÓN | P4: TIPO | Q4: IMPORTE
A5: 1 | B5: 46295 | C5: DEPÓSITO DE VENTAS 30-SEP | D5: 12500 | E5: =IF(B5="","",MAX(0,IF(FORMATO!$B$7="",TODAY(),FORMATO!$B$7)-B5)) | G5: 1 | H5: 46293 | I5: CHEQUE 1045 PAPELERA DEL CENTRO | J5: 5400 | K5: =IF(H5="","",MAX(0,IF(FORMATO!$B$7="",TODAY(),FORMATO!$B$7)-H5)) | M5: 1 | N5: 46295 | O5: INTERESES GANADOS | P5: ABONO | Q5: 320
A6: 2 | E6: =IF(B6="","",MAX(0,IF(FORMATO!$B$7="",TODAY(),FORMATO!$B$7)-B6)) | G6: 2 | H6: 46294 | I6: CHEQUE 1046 DISTRIBUIDORA PLUMA | J6: 2900.25 | K6: =IF(H6="","",MAX(0,IF(FORMATO!$B$7="",TODAY(),FORMATO!$B$7)-H6)) | M6: 2 | N6: 46295 | O6: COMISIÓN POR MANEJO DE CUENTA | P6: CARGO | Q6: 150
A7: 3 | E7: =IF(B7="","",MAX(0,IF(FORMATO!$B$7="",TODAY(),FORMATO!$B$7)-B7)) | G7: 3 | K7: =IF(H7="","",MAX(0,IF(FORMATO!$B$7="",TODAY(),FORMATO!$B$7)-H7)) | M7: 3
A8: 4 | E8: =IF(B8="","",MAX(0,IF(FORMATO!$B$7="",TODAY(),FORMATO!$B$7)-B8)) | G8: 4 | K8: =IF(H8="","",MAX(0,IF(FORMATO!$B$7="",TODAY(),FORMATO!$B$7)-H8)) | M8: 4
A9: 5 | E9: =IF(B9="","",MAX(0,IF(FORMATO!$B$7="",TODAY(),FORMATO!$B$7)-B9)) | G9: 5 | K9: =IF(H9="","",MAX(0,IF(FORMATO!$B$7="",TODAY(),FORMATO!$B$7)-H9)) | M9: 5
A10: 6 | E10: =IF(B10="","",MAX(0,IF(FORMATO!$B$7="",TODAY(),FORMATO!$B$7)-B10)) | G10: 6 | K10: =IF(H10="","",MAX(0,IF(FORMATO!$B$7="",TODAY(),FORMATO!$B$7)-H10)) | M10: 6
A11: 7 | E11: =IF(B11="","",MAX(0,IF(FORMATO!$B$7="",TODAY(),FORMATO!$B$7)-B11)) | G11: 7 | K11: =IF(H11="","",MAX(0,IF(FORMATO!$B$7="",TODAY(),FORMATO!$B$7)-H11)) | M11: 7
A12: 8 | E12: =IF(B12="","",MAX(0,IF(FORMATO!$B$7="",TODAY(),FORMATO!$B$7)-B12)) | G12: 8 | K12: =IF(H12="","",MAX(0,IF(FORMATO!$B$7="",TODAY(),FORMATO!$B$7)-H12)) | M12: 8
A13: 9 | E13: =IF(B13="","",MAX(0,IF(FORMATO!$B$7="",TODAY(),FORMATO!$B$7)-B13)) | G13: 9 | K13: =IF(H13="","",MAX(0,IF(FORMATO!$B$7="",TODAY(),FORMATO!$B$7)-H13)) | M13: 9
A14: 10 | E14: =IF(B14="","",MAX(0,IF(FORMATO!$B$7="",TODAY(),FORMATO!$B$7)-B14)) | G14: 10 | K14: =IF(H14="","",MAX(0,IF(FORMATO!$B$7="",TODAY(),FORMATO!$B$7)-H14)) | M14: 10
A15: 11 | E15: =IF(B15="","",MAX(0,IF(FORMATO!$B$7="",TODAY(),FORMATO!$B$7)-B15)) | G15: 11 | K15: =IF(H15="","",MAX(0,IF(FORMATO!$B$7="",TODAY(),FORMATO!$B$7)-H15)) | M15: 11
A16: 12 | E16: =IF(B16="","",MAX(0,IF(FORMATO!$B$7="",TODAY(),FORMATO!$B$7)-B16)) | G16: 12 | K16: =IF(H16="","",MAX(0,IF(FORMATO!$B$7="",TODAY(),FORMATO!$B$7)-H16)) | M16: 12
A17: 13 | E17: =IF(B17="","",MAX(0,IF(FORMATO!$B$7="",TODAY(),FORMATO!$B$7)-B17)) | G17: 13 | K17: =IF(H17="","",MAX(0,IF(FORMATO!$B$7="",TODAY(),FORMATO!$B$7)-H17)) | M17: 13
A18: 14 | E18: =IF(B18="","",MAX(0,IF(FORMATO!$B$7="",TODAY(),FORMATO!$B$7)-B18)) | G18: 14 | K18: =IF(H18="","",MAX(0,IF(FORMATO!$B$7="",TODAY(),FORMATO!$B$7)-H18)) | M18: 14
... A54: 50 | E54: =IF(B54="","",MAX(0,IF(FORMATO!$B$7="",TODAY(),FORMATO!$B$7)-B54)) | G54: 50 | K54: =IF(H54="","",MAX(0,IF(FORMATO!$B$7="",TODAY(),FORMATO!$B$7)-H54)) | M54: 50
C55: TOTAL | D55: =SUM(D5:D54) | I55: TOTAL | J55: =SUM(J5:J54) | P55: TOTAL | Q55: =SUM(Q5:Q54)

Sheet AYUDA
B1: AYUDA Y PREGUNTAS FRECUENTES
B2: CONCILIACIÓN BANCARIA
B5: PREGUNTAS FRECUENTES
C6: ¿Qué es una partida en tránsito? | D6: Un movimiento registrado en tus libros que el banco aún no refleja (por ejemplo, un cheque que no se ha cobrado).
C7: ¿Qué hago si la diferencia no es cero? | D7: Revisa que no falten comisiones, intereses o IVA bancarios por registrar y que ningún movimiento esté duplicado.
C8: ¿Por qué no puedo escribir en algunas celdas? | D8: La hoja está protegida para que no se borren fórmulas por accidente. Solo se editan las celdas de captura (color crema). Si necesitas modificar algo más: pestaña Revisar > Desproteger hoja (no tiene contraseña).
C9: ¿Cómo agrego mi logotipo? | D9: Haz clic en el recuadro punteado de la esquina superior derecha del formato y usa Insertar > Imágenes. Ajusta el tamaño sin salirte del recuadro.
C10: ¿Cómo lo imprimo o lo convierto a PDF? | D10: Archivo > Imprimir (ya está ajustado a una hoja de ancho). Para PDF elige 'Microsoft Print to PDF' o Archivo > Exportar > PDF.
C11: ¿Con qué versiones de Excel funciona? | D11: Excel 2016, 2019, 2021 y Microsoft 365 (Windows y Mac). Funciona en LibreOffice y Google Sheets, aunque algunas gráficas y formatos pueden verse distintos.
C12: ¿Puedo cambiar la letra? | D12: El diseño usa la fuente Arial, disponible en Windows, Mac y Google Sheets. Si necesitas otra, selecciona todo (Ctrl+E) y cambia la fuente; no afecta el funcionamiento.
C13: ¿Puedo usarlo en varias empresas o por varios años? | D13: Sí. Guarda una copia del archivo por empresa o por periodo (Archivo > Guardar como) y deja el original en blanco como plantilla maestra.
B15: GLOSARIO
C16: SALDO SEGÚN BANCO | D16: Saldo final del estado de cuenta.
C17: SALDO SEGÚN LIBROS | D17: Saldo de tu contabilidad en la cuenta de bancos.
C18: DEPÓSITO EN TRÁNSITO | D18: Depósito en libros que el banco aún no abona.
C19: CHEQUE EN TRÁNSITO | D19: Cheque emitido que aún no se cobra.
B21: LISTA DE VERIFICACIÓN (marca ☑ al completar)
B22: ☐ | C22: Estado de cuenta del mes descargado
B23: ☐ | C23: Saldos capturados
B24: ☐ | C24: Partidas en tránsito listadas
B25: ☐ | C25: Diferencia en cero y firmada
