Workbook

Sheet PORTADA
B2: FORMATOS ADMINISTRATIVOS | E2: VERSIÓN 2.0 · MÉXICO
B4: PRESUPUESTO ANUAL
B6: Formato administrativo profesional · editable · listo para imprimir
C9: FÓRMULAS AUTOMÁTICAS | D9: LISTAS DESPLEGABLES | E9: HOJAS PROTEGIDAS | F9: LISTO PARA IMPRIMIR
B15: ¿QUÉ INCLUYE ESTE ARCHIVO?
B16: ▸ | C16: FORMATO | D16: Hoja principal de captura. Aquí registras tu información; las celdas grises calculan solas.
B17: ▸ | C17: RESUMEN | D17: Tablero con indicadores y gráficas que se actualizan automáticamente con tus datos.
B18: ▸ | C18: AYUDA | D18: Preguntas frecuentes, glosario y lista de verificación para cerrar tu periodo.
B20: FICHA TÉCNICA
C21: Capacidad | D21: 10 conceptos x 12 meses
C22: Compatibilidad | D22: Excel 2016, 2019, 2021 y Microsoft 365 (Windows y Mac)
C23: Idioma y moneda | D23: Español (México) · Pesos mexicanos (MXN) · IVA 16%
C24: Protección | D24: Hojas protegidas sin contraseña (Revisar > Desproteger hoja)
C25: Fuente | D25: Arial (disponible en Windows, Mac y Google Sheets)
B27: CÓMO USARLO
B28: 1 | C28: Por cada concepto hay dos renglones: Presup. (lo planeado) y Real (lo ejercido).
B29: 2 | C29: Captura mes a mes. La columna Variación muestra Real - Presupuesto del primer renglón de cada concepto.
B30: 3 | C30: En gastos, una variación positiva (rojo) significa que te pasaste del presupuesto; en ventas, positiva es favorable.
B31: 4 | C31: El % de ejecución indica qué parte del presupuesto anual ya se ejerció.
B32: 5 | C32: Personaliza: inserta tu logotipo en el recuadro punteado de la esquina superior derecha (Insertar > Imágenes) y captura los datos de tu empresa en las celdas de captura.
B34: RECOMENDACIONES DE USO
B35: ✓ | C35: Parte de los resultados del año anterior y ajusta por inflación y metas de ventas.
B36: ✓ | C36: Revisa la variación cada mes y toma acciones si pasa del 10%.
B37: ✓ | C37: Separa gastos fijos y variables para identificar dónde puedes ahorrar.
B38: ✓ | C38: Actualiza la proyección trimestralmente (reforecast).
B40: LEYENDA DE COLORES
C41: CELDA DE CAPTURA: escribe aquí.
C42: CÁLCULO AUTOMÁTICO: no la modifiques.
C43: ENCABEZADOS Y TÍTULOS.
C44: * CAMPO OBLIGATORIO: complétalo antes de imprimir o enviar.
B46: Formatos administrativos · Para uso interno de tu empresa

Sheet FORMATO
A1: PRESUPUESTO ANUAL: PRESUPUESTADO VS REAL | P1: INSERTE SU LOGO (clic derecho > Insertar imagen)
A2: Captura presupuesto y gasto real por mes; la variación se calcula sola
A4: EMPRESA / ÁREA | B4: COMERCIALIZADORA EJEMPLO S.A. DE C.V. | F4: AÑO | G4: 2026
A7: CONCEPTO | B7: ENE | C7: FEB | D7: MAR | E7: ABR | F7: MAY | G7: JUN | H7: JUL | I7: AGO | J7: SEP | K7: OCT | L7: NOV | M7: DIC | N7: PRESUP. ANUAL | O7: REAL ANUAL | P7: VARIACIÓN | Q7: % EJEC.
A8: VENTAS - PRESUP. | B8: 220000 | C8: 220000 | D8: 220000 | E8: 220000 | F8: 220000 | G8: 220000 | H8: 220000 | I8: 220000 | J8: 220000 | K8: 220000 | L8: 220000 | M8: 220000 | N8: =SUM(B8:M8) | O8: =SUM(B9:M9) | P8: =O8-N8 | Q8: =IF(N8=0,"",O8/N8)
A9: VENTAS - REAL | B9: 228800 | C9: 233200 | D9: 237600 | E9: 228800 | F9: 233200 | G9: 237600 | H9: 228800 | I9: 233200 | J9: 237600
A10: COSTO DE VENTAS - PRESUP. | B10: 120000 | C10: 120000 | D10: 120000 | E10: 120000 | F10: 120000 | G10: 120000 | H10: 120000 | I10: 120000 | J10: 120000 | K10: 120000 | L10: 120000 | M10: 120000 | N10: =SUM(B10:M10) | O10: =SUM(B11:M11) | P10: =O10-N10 | Q10: =IF(N10=0,"",O10/N10)
A11: COSTO DE VENTAS - REAL | B11: 114000 | C11: 116400 | D11: 118800 | E11: 114000 | F11: 116400 | G11: 118800 | H11: 114000 | I11: 116400 | J11: 118800
A12: SUELDOS Y SALARIOS - PRESUP. | B12: 62000 | C12: 62000 | D12: 62000 | E12: 62000 | F12: 62000 | G12: 62000 | H12: 62000 | I12: 62000 | J12: 62000 | K12: 62000 | L12: 62000 | M12: 62000 | N12: =SUM(B12:M12) | O12: =SUM(B13:M13) | P12: =O12-N12 | Q12: =IF(N12=0,"",O12/N12)
A13: SUELDOS Y SALARIOS - REAL | B13: 63240 | C13: 64480 | D13: 65720 | E13: 63240 | F13: 64480 | G13: 65720 | H13: 63240 | I13: 64480 | J13: 65720
A14: RENTA - PRESUP. | B14: 22000 | C14: 22000 | D14: 22000 | E14: 22000 | F14: 22000 | G14: 22000 | H14: 22000 | I14: 22000 | J14: 22000 | K14: 22000 | L14: 22000 | M14: 22000 | N14: =SUM(B14:M14) | O14: =SUM(B15:M15) | P14: =O14-N14 | Q14: =IF(N14=0,"",O14/N14)
A15: RENTA - REAL | B15: 24200 | C15: 24640 | D15: 25080 | E15: 24200 | F15: 24640 | G15: 25080 | H15: 24200 | I15: 24640 | J15: 25080
A16: SERVICIOS - PRESUP. | B16: 9000 | C16: 9000 | D16: 9000 | E16: 9000 | F16: 9000 | G16: 9000 | H16: 9000 | I16: 9000 | J16: 9000 | K16: 9000 | L16: 9000 | M16: 9000 | N16: =SUM(B16:M16) | O16: =SUM(B17:M17) | P16: =O16-N16 | Q16: =IF(N16=0,"",O16/N16)
A17: SERVICIOS - REAL | B17: 9000 | C17: 9180 | D17: 9360 | E17: 9000 | F17: 9180 | G17: 9360 | H17: 9000 | I17: 9180 | J17: 9360
A18: PUBLICIDAD Y MERCADOTECNIA - PRESUP. | B18: 14000 | C18: 14000 | D18: 14000 | E18: 14000 | F18: 14000 | G18: 14000 | H18: 14000 | I18: 14000 | J18: 14000 | K18: 14000 | L18: 14000 | M18: 14000 | N18: =SUM(B18:M18) | O18: =SUM(B19:M19) | P18: =O18-N18 | Q18: =IF(N18=0,"",O18/N18)
A19: PUBLICIDAD Y MERCADOTECNIA - REAL | B19: 12740 | C19: 13020 | D19: 13300 | E19: 12740 | F19: 13020 | G19: 13300 | H19: 12740 | I19: 13020 | J19: 13300
A20: MANTENIMIENTO - PRESUP. | B20: 6000 | C20: 6000 | D20: 6000 | E20: 6000 | F20: 6000 | G20: 6000 | H20: 6000 | I20: 6000 | J20: 6000 | K20: 6000 | L20: 6000 | M20: 6000 | N20: =SUM(B20:M20) | O20: =SUM(B21:M21) | P20: =O20-N20 | Q20: =IF(N20=0,"",O20/N20)
A21: MANTENIMIENTO - REAL | B21: 6780 | C21: 6900 | D21: 7020 | E21: 6780 | F21: 6900 | G21: 7020 | H21: 6780 | I21: 6900 | J21: 7020
A22: PAPELERÍA Y OFICINA - PRESUP. | B22: 4000 | C22: 4000 | D22: 4000 | E22: 4000 | F22: 4000 | G22: 4000 | H22: 4000 | I22: 4000 | J22: 4000 | K22: 4000 | L22: 4000 | M22: 4000 | N22: =SUM(B22:M22) | O22: =SUM(B23:M23) | P22: =O22-N22 | Q22: =IF(N22=0,"",O22/N22)
A23: PAPELERÍA Y OFICINA - REAL | B23: 4240 | C23: 4320 | D23: 4400 | E23: 4240 | F23: 4320 | G23: 4400 | H23: 4240 | I23: 4320 | J23: 4400
A24: IMPUESTOS Y DERECHOS - PRESUP. | B24: 16000 | C24: 16000 | D24: 16000 | E24: 16000 | F24: 16000 | G24: 16000 | H24: 16000 | I24: 16000 | J24: 16000 | K24: 16000 | L24: 16000 | M24: 16000 | N24: =SUM(B24:M24) | O24: =SUM(B25:M25) | P24: =O24-N24 | Q24: =IF(N24=0,"",O24/N24)
A25: IMPUESTOS Y DERECHOS - REAL | B25: 15840 | C25: 16160 | D25: 16480 | E25: 15840 | F25: 16160 | G25: 16480 | H25: 15840 | I25: 16160 | J25: 16480
A26: OTROS GASTOS - PRESUP. | B26: 7000 | C26: 7000 | D26: 7000 | E26: 7000 | F26: 7000 | G26: 7000 | H26: 7000 | I26: 7000 | J26: 7000 | K26: 7000 | L26: 7000 | M26: 7000 | N26: =SUM(B26:M26) | O26: =SUM(B27:M27) | P26: =O26-N26 | Q26: =IF(N26=0,"",O26/N26)
A27: OTROS GASTOS - REAL | B27: 8260 | C27: 8400 | D27: 8540 | E27: 8260 | F27: 8400 | G27: 8540 | H27: 8260 | I27: 8400 | J27: 8540

Sheet RESUMEN
A1: RESUMEN DEL PRESUPUESTO | H1: INSERTE SU LOGO (clic derecho > Insertar imagen)
A2: Presupuestado vs. real por concepto
B4: VENTAS PRESUPUESTADAS | D4: VENTAS REALES | F4: GASTO PRESUPUESTADO | H4: GASTO REAL
B5: =C9 | D5: =D9 | F5: =SUM(C10:C18) | H5: =SUM(D10:D18)
B7: =IF(SUM(C9:C18)=0,"Captura el presupuesto y el real en la hoja FORMATO para ver el análisis automático.","Mayor sobre-ejercicio: "&IF(MAX(E9:E18)<=0,"ninguno",INDEX(B9:B18,MATCH(MAX(E9:E18),E9:E18,0)))&". Ejecución global de ventas: "&TEXT(IFERROR(D9/C9,0),"0%")&".")
B8: CONCEPTO | C8: PRESUPUESTO | D8: REAL | E8: VARIACIÓN | F8: % EJEC.
B9: VENTAS | C9: =FORMATO!N8 | D9: =FORMATO!O8 | E9: =D9-C9 | F9: =IF(C9=0,"",D9/C9)
B10: COSTO DE VENTAS | C10: =FORMATO!N10 | D10: =FORMATO!O10 | E10: =D10-C10 | F10: =IF(C10=0,"",D10/C10)
B11: SUELDOS Y SALARIOS | C11: =FORMATO!N12 | D11: =FORMATO!O12 | E11: =D11-C11 | F11: =IF(C11=0,"",D11/C11)
B12: RENTA | C12: =FORMATO!N14 | D12: =FORMATO!O14 | E12: =D12-C12 | F12: =IF(C12=0,"",D12/C12)
B13: SERVICIOS | C13: =FORMATO!N16 | D13: =FORMATO!O16 | E13: =D13-C13 | F13: =IF(C13=0,"",D13/C13)
B14: PUBLICIDAD Y MERCADOTECNIA | C14: =FORMATO!N18 | D14: =FORMATO!O18 | E14: =D14-C14 | F14: =IF(C14=0,"",D14/C14)
B15: MANTENIMIENTO | C15: =FORMATO!N20 | D15: =FORMATO!O20 | E15: =D15-C15 | F15: =IF(C15=0,"",D15/C15)
B16: PAPELERÍA Y OFICINA | C16: =FORMATO!N22 | D16: =FORMATO!O22 | E16: =D16-C16 | F16: =IF(C16=0,"",D16/C16)
B17: IMPUESTOS Y DERECHOS | C17: =FORMATO!N24 | D17: =FORMATO!O24 | E17: =D17-C17 | F17: =IF(C17=0,"",D17/C17)
B18: OTROS GASTOS | C18: =FORMATO!N26 | D18: =FORMATO!O26 | E18: =D18-C18 | F18: =IF(C18=0,"",D18/C18)

Sheet AYUDA
B1: AYUDA Y PREGUNTAS FRECUENTES
B2: PRESUPUESTO ANUAL
B5: PREGUNTAS FRECUENTES
C6: ¿Cómo leo la variación? | D6: Real - Presupuesto. En gastos, positiva significa que te pasaste; en ventas, positiva es favorable.
C7: ¿Puedo agregar conceptos? | D7: Cambia el nombre de uno de los 10 conceptos disponibles.
C8: ¿Por qué no puedo escribir en algunas celdas? | D8: La hoja está protegida para que no se borren fórmulas por accidente. Solo se editan las celdas de captura (color crema). Si necesitas modificar algo más: pestaña Revisar > Desproteger hoja (no tiene contraseña).
C9: ¿Cómo agrego mi logotipo? | D9: Haz clic en el recuadro punteado de la esquina superior derecha del formato y usa Insertar > Imágenes. Ajusta el tamaño sin salirte del recuadro.
C10: ¿Cómo lo imprimo o lo convierto a PDF? | D10: Archivo > Imprimir (ya está ajustado a una hoja de ancho). Para PDF elige 'Microsoft Print to PDF' o Archivo > Exportar > PDF.
C11: ¿Con qué versiones de Excel funciona? | D11: Excel 2016, 2019, 2021 y Microsoft 365 (Windows y Mac). Funciona en LibreOffice y Google Sheets, aunque algunas gráficas y formatos pueden verse distintos.
C12: ¿Puedo cambiar la letra? | D12: El diseño usa la fuente Arial, disponible en Windows, Mac y Google Sheets. Si necesitas otra, selecciona todo (Ctrl+E) y cambia la fuente; no afecta el funcionamiento.
C13: ¿Puedo usarlo en varias empresas o por varios años? | D13: Sí. Guarda una copia del archivo por empresa o por periodo (Archivo > Guardar como) y deja el original en blanco como plantilla maestra.
B15: GLOSARIO
C16: PRESUPUESTO | D16: Plan de ingresos y gastos.
C17: VARIACIÓN | D17: Diferencia entre lo real y lo presupuestado.
C18: % DE EJECUCIÓN | D18: Real / presupuesto.
B20: LISTA DE VERIFICACIÓN (marca ☑ al completar)
B21: ☐ | C21: Presupuesto aprobado
B22: ☐ | C22: Real capturado al cierre de cada mes
B23: ☐ | C23: Variaciones >10% explicadas
B24: ☐ | C24: Reforecast trimestral
