Workbook

Sheet PORTADA
B2: FORMATOS ADMINISTRATIVOS | E2: VERSIÓN 2.0 · MÉXICO
B4: ACTIVOS FIJOS
B6: Formato administrativo profesional · editable · listo para imprimir
C9: FÓRMULAS AUTOMÁTICAS | D9: LISTAS DESPLEGABLES | E9: HOJAS PROTEGIDAS | F9: LISTO PARA IMPRIMIR
B15: ¿QUÉ INCLUYE ESTE ARCHIVO?
B16: ▸ | C16: FORMATO | D16: Hoja principal de captura. Aquí registras tu información; las celdas grises calculan solas.
B17: ▸ | C17: TASAS | D17: Tabla de tasas de depreciación de referencia; edítala según tu criterio contable.
B18: ▸ | C18: RESUMEN | D18: Tablero con indicadores y gráficas que se actualizan automáticamente con tus datos.
B19: ▸ | C19: AYUDA | D19: Preguntas frecuentes, glosario y lista de verificación para cerrar tu periodo.
B21: FICHA TÉCNICA
C22: Capacidad | D22: 150 activos
C23: Compatibilidad | D23: Excel 2016, 2019, 2021 y Microsoft 365 (Windows y Mac)
C24: Idioma y moneda | D24: Español (México) · Pesos mexicanos (MXN) · IVA 16%
C25: Protección | D25: Hojas protegidas sin contraseña (Revisar > Desproteger hoja)
C26: Fuente | D26: Arial (disponible en Windows, Mac y Google Sheets)
B28: CÓMO USARLO
B29: 1 | C29: Registra cada activo con fecha de adquisición, costo (sin IVA) y categoría.
B30: 2 | C30: La tasa se toma de la hoja 'Tasas' (referencia de porcentajes máximos de la LISR); edítala según tu criterio contable.
B31: 3 | C31: Depreciación acumulada = depreciación anual x años en uso, sin exceder el costo.
B32: 4 | C32: Es una herramienta de control administrativo; consulta a tu contador para efectos fiscales.
B33: 5 | C33: Personaliza: inserta tu logotipo en el recuadro punteado de la esquina superior derecha (Insertar > Imágenes) y captura los datos de tu empresa en las celdas de captura.
B35: RECOMENDACIONES DE USO
B36: ✓ | C36: Etiqueta físicamente cada activo con su código.
B37: ✓ | C37: Realiza inventario físico de activos al menos una vez al año.
B38: ✓ | C38: Registra bajas y ventas con fecha y documento.
B39: ✓ | C39: Las tasas de la hoja TASAS son una referencia; confirma con tu contador.
B41: LEYENDA DE COLORES
C42: CELDA DE CAPTURA: escribe aquí.
C43: CÁLCULO AUTOMÁTICO: no la modifiques.
C44: ENCABEZADOS Y TÍTULOS.
C45: * CAMPO OBLIGATORIO: complétalo antes de imprimir o enviar.
B47: Formatos administrativos · Para uso interno de tu empresa

Sheet FORMATO
A1: CONTROL DE ACTIVOS FIJOS Y DEPRECIACIÓN | K1: INSERTE SU LOGO (clic derecho > Insertar imagen)
A2: Depreciación en línea recta con tasas máximas de la LISR como referencia
A4: EMPRESA * | B4: COMERCIALIZADORA EJEMPLO S.A. DE C.V. | F4: FECHA DE CORTE | G4: 46302
A6: NO. | B6: CÓDIGO | C6: DESCRIPCIÓN | D6: CATEGORÍA | E6: FECHA ADQUISICIÓN | F6: COSTO (MOI) | G6: TASA ANUAL | H6: DEP. ANUAL | I6: AÑOS EN USO | J6: DEP. ACUMULADA | K6: VALOR EN LIBROS | L6: UBICACIÓN / RESPONSABLE
A7: 1 | B7: AF-001 | C7: LAPTOP DELL LATITUDE 5440 | D7: EQUIPO DE CÓMPUTO | E7: 45337 | F7: 28900 | G7: =IF(D7="","",IFERROR(VLOOKUP(D7,TASAS!$A$2:$B$10,2,FALSE),0)) | H7: =IF(F7="","",F7*G7) | I7: =IF(E7="","",MAX(0,($G$4-E7)/365)) | J7: =IF(F7="","",MIN(F7,H7*I7)) | K7: =IF(F7="","",F7-J7) | L7: ADMINISTRACIÓN
A8: 2 | B8: AF-002 | C8: ESCRITORIO EJECUTIVO | D8: MOBILIARIO Y EQUIPO DE OFICINA | E8: 44713 | F8: 4890 | G8: =IF(D8="","",IFERROR(VLOOKUP(D8,TASAS!$A$2:$B$10,2,FALSE),0)) | H8: =IF(F8="","",F8*G8) | I8: =IF(E8="","",MAX(0,($G$4-E8)/365)) | J8: =IF(F8="","",MIN(F8,H8*I8)) | K8: =IF(F8="","",F8-J8) | L8: DIRECCIÓN
A9: 3 | B9: AF-003 | C9: CAMIONETA NISSAN NP300 | D9: AUTOMÓVILES | E9: 44936 | F9: 389000 | G9: =IF(D9="","",IFERROR(VLOOKUP(D9,TASAS!$A$2:$B$10,2,FALSE),0)) | H9: =IF(F9="","",F9*G9) | I9: =IF(E9="","",MAX(0,($G$4-E9)/365)) | J9: =IF(F9="","",MIN(F9,H9*I9)) | K9: =IF(F9="","",F9-J9) | L9: REPARTO
A10: 4 | B10: AF-004 | C10: IMPRESORA MULTIFUNCIONAL | D10: EQUIPO DE CÓMPUTO | E10: 45736 | F10: 12800 | G10: =IF(D10="","",IFERROR(VLOOKUP(D10,TASAS!$A$2:$B$10,2,FALSE),0)) | H10: =IF(F10="","",F10*G10) | I10: =IF(E10="","",MAX(0,($G$4-E10)/365)) | J10: =IF(F10="","",MIN(F10,H10*I10)) | K10: =IF(F10="","",F10-J10) | L10: RECEPCIÓN
A11: 5 | B11: AF-005 | C11: AIRE ACONDICIONADO 2 TON | D11: MAQUINARIA Y EQUIPO | E11: 44328 | F11: 21500 | G11: =IF(D11="","",IFERROR(VLOOKUP(D11,TASAS!$A$2:$B$10,2,FALSE),0)) | H11: =IF(F11="","",F11*G11) | I11: =IF(E11="","",MAX(0,($G$4-E11)/365)) | J11: =IF(F11="","",MIN(F11,H11*I11)) | K11: =IF(F11="","",F11-J11) | L11: SALA DE JUNTAS
A12: 6 | G12: =IF(D12="","",IFERROR(VLOOKUP(D12,TASAS!$A$2:$B$10,2,FALSE),0)) | H12: =IF(F12="","",F12*G12) | I12: =IF(E12="","",MAX(0,($G$4-E12)/365)) | J12: =IF(F12="","",MIN(F12,H12*I12)) | K12: =IF(F12="","",F12-J12)
A13: 7 | G13: =IF(D13="","",IFERROR(VLOOKUP(D13,TASAS!$A$2:$B$10,2,FALSE),0)) | H13: =IF(F13="","",F13*G13) | I13: =IF(E13="","",MAX(0,($G$4-E13)/365)) | J13: =IF(F13="","",MIN(F13,H13*I13)) | K13: =IF(F13="","",F13-J13)
A14: 8 | G14: =IF(D14="","",IFERROR(VLOOKUP(D14,TASAS!$A$2:$B$10,2,FALSE),0)) | H14: =IF(F14="","",F14*G14) | I14: =IF(E14="","",MAX(0,($G$4-E14)/365)) | J14: =IF(F14="","",MIN(F14,H14*I14)) | K14: =IF(F14="","",F14-J14)
A15: 9 | G15: =IF(D15="","",IFERROR(VLOOKUP(D15,TASAS!$A$2:$B$10,2,FALSE),0)) | H15: =IF(F15="","",F15*G15) | I15: =IF(E15="","",MAX(0,($G$4-E15)/365)) | J15: =IF(F15="","",MIN(F15,H15*I15)) | K15: =IF(F15="","",F15-J15)
A16: 10 | G16: =IF(D16="","",IFERROR(VLOOKUP(D16,TASAS!$A$2:$B$10,2,FALSE),0)) | H16: =IF(F16="","",F16*G16) | I16: =IF(E16="","",MAX(0,($G$4-E16)/365)) | J16: =IF(F16="","",MIN(F16,H16*I16)) | K16: =IF(F16="","",F16-J16)
A17: 11 | G17: =IF(D17="","",IFERROR(VLOOKUP(D17,TASAS!$A$2:$B$10,2,FALSE),0)) | H17: =IF(F17="","",F17*G17) | I17: =IF(E17="","",MAX(0,($G$4-E17)/365)) | J17: =IF(F17="","",MIN(F17,H17*I17)) | K17: =IF(F17="","",F17-J17)
A18: 12 | G18: =IF(D18="","",IFERROR(VLOOKUP(D18,TASAS!$A$2:$B$10,2,FALSE),0)) | H18: =IF(F18="","",F18*G18) | I18: =IF(E18="","",MAX(0,($G$4-E18)/365)) | J18: =IF(F18="","",MIN(F18,H18*I18)) | K18: =IF(F18="","",F18-J18)
A19: 13 | G19: =IF(D19="","",IFERROR(VLOOKUP(D19,TASAS!$A$2:$B$10,2,FALSE),0)) | H19: =IF(F19="","",F19*G19) | I19: =IF(E19="","",MAX(0,($G$4-E19)/365)) | J19: =IF(F19="","",MIN(F19,H19*I19)) | K19: =IF(F19="","",F19-J19)
A20: 14 | G20: =IF(D20="","",IFERROR(VLOOKUP(D20,TASAS!$A$2:$B$10,2,FALSE),0)) | H20: =IF(F20="","",F20*G20) | I20: =IF(E20="","",MAX(0,($G$4-E20)/365)) | J20: =IF(F20="","",MIN(F20,H20*I20)) | K20: =IF(F20="","",F20-J20)
A21: 15 | G21: =IF(D21="","",IFERROR(VLOOKUP(D21,TASAS!$A$2:$B$10,2,FALSE),0)) | H21: =IF(F21="","",F21*G21) | I21: =IF(E21="","",MAX(0,($G$4-E21)/365)) | J21: =IF(F21="","",MIN(F21,H21*I21)) | K21: =IF(F21="","",F21-J21)
A22: 16 | G22: =IF(D22="","",IFERROR(VLOOKUP(D22,TASAS!$A$2:$B$10,2,FALSE),0)) | H22: =IF(F22="","",F22*G22) | I22: =IF(E22="","",MAX(0,($G$4-E22)/365)) | J22: =IF(F22="","",MIN(F22,H22*I22)) | K22: =IF(F22="","",F22-J22)
A23: 17 | G23: =IF(D23="","",IFERROR(VLOOKUP(D23,TASAS!$A$2:$B$10,2,FALSE),0)) | H23: =IF(F23="","",F23*G23) | I23: =IF(E23="","",MAX(0,($G$4-E23)/365)) | J23: =IF(F23="","",MIN(F23,H23*I23)) | K23: =IF(F23="","",F23-J23)
... A156: 150 | G156: =IF(D156="","",IFERROR(VLOOKUP(D156,TASAS!$A$2:$B$10,2,FALSE),0)) | H156: =IF(F156="","",F156*G156) | I156: =IF(E156="","",MAX(0,($G$4-E156)/365)) | J156: =IF(F156="","",MIN(F156,H156*I156)) | K156: =IF(F156="","",F156-J156)
E157: TOTAL | F157: =SUM(F7:F156) | H157: =SUM(H7:H156) | J157: =SUM(J7:J156) | K157: =SUM(K7:K156)

Sheet TASAS
A1: CATEGORÍA | B1: TASA ANUAL (REF.)
A2: MOBILIARIO Y EQUIPO DE OFICINA | B2: 0.1
A3: EQUIPO DE CÓMPUTO | B3: 0.3
A4: AUTOMÓVILES | B4: 0.25
A5: MAQUINARIA Y EQUIPO | B5: 0.1
A6: EQUIPO DE COMUNICACIÓN | B6: 0.1
A7: EDIFICIOS | B7: 0.05
A8: HERRAMIENTAS | B8: 0.35
A9: OTROS | B9: 0.1

Sheet RESUMEN
A1: RESUMEN DE ACTIVOS FIJOS | H1: INSERTE SU LOGO (clic derecho > Insertar imagen)
A2: Inversión, depreciación y valor en libros por categoría
B4: INVERSIÓN (MOI) | D4: DEP. ACUMULADA | F4: VALOR EN LIBROS | H4: ACTIVOS
B5: =FORMATO!F157 | D5: =FORMATO!J157 | F5: =FORMATO!K157 | H5: =COUNT(FORMATO!F7:F156)
B25: CATEGORÍA | C25: COSTO (MOI) | D25: VALOR EN LIBROS
B26: =TASAS!A2 | C26: =SUMIF(FORMATO!$D$7:$D$156,B26,FORMATO!$F$7:$F$156) | D26: =SUMIF(FORMATO!$D$7:$D$156,B26,FORMATO!$K$7:$K$156)
B27: =TASAS!A3 | C27: =SUMIF(FORMATO!$D$7:$D$156,B27,FORMATO!$F$7:$F$156) | D27: =SUMIF(FORMATO!$D$7:$D$156,B27,FORMATO!$K$7:$K$156)
B28: =TASAS!A4 | C28: =SUMIF(FORMATO!$D$7:$D$156,B28,FORMATO!$F$7:$F$156) | D28: =SUMIF(FORMATO!$D$7:$D$156,B28,FORMATO!$K$7:$K$156)
B29: =TASAS!A5 | C29: =SUMIF(FORMATO!$D$7:$D$156,B29,FORMATO!$F$7:$F$156) | D29: =SUMIF(FORMATO!$D$7:$D$156,B29,FORMATO!$K$7:$K$156)
B30: =TASAS!A6 | C30: =SUMIF(FORMATO!$D$7:$D$156,B30,FORMATO!$F$7:$F$156) | D30: =SUMIF(FORMATO!$D$7:$D$156,B30,FORMATO!$K$7:$K$156)
B31: =TASAS!A7 | C31: =SUMIF(FORMATO!$D$7:$D$156,B31,FORMATO!$F$7:$F$156) | D31: =SUMIF(FORMATO!$D$7:$D$156,B31,FORMATO!$K$7:$K$156)
B32: =TASAS!A8 | C32: =SUMIF(FORMATO!$D$7:$D$156,B32,FORMATO!$F$7:$F$156) | D32: =SUMIF(FORMATO!$D$7:$D$156,B32,FORMATO!$K$7:$K$156)
B33: =TASAS!A9 | C33: =SUMIF(FORMATO!$D$7:$D$156,B33,FORMATO!$F$7:$F$156) | D33: =SUMIF(FORMATO!$D$7:$D$156,B33,FORMATO!$K$7:$K$156)

Sheet AYUDA
B1: AYUDA Y PREGUNTAS FRECUENTES
B2: ACTIVOS FIJOS
B5: PREGUNTAS FRECUENTES
C6: ¿Qué es el MOI? | D6: Monto original de la inversión: costo de adquisición sin IVA más gastos de instalación.
C7: ¿Cómo doy de baja un activo? | D7: Escribe la fecha de baja en tu bitácora y retira el renglón o márcalo en Ubicación.
C8: ¿Por qué no puedo escribir en algunas celdas? | D8: La hoja está protegida para que no se borren fórmulas por accidente. Solo se editan las celdas de captura (color crema). Si necesitas modificar algo más: pestaña Revisar > Desproteger hoja (no tiene contraseña).
C9: ¿Cómo agrego mi logotipo? | D9: Haz clic en el recuadro punteado de la esquina superior derecha del formato y usa Insertar > Imágenes. Ajusta el tamaño sin salirte del recuadro.
C10: ¿Cómo lo imprimo o lo convierto a PDF? | D10: Archivo > Imprimir (ya está ajustado a una hoja de ancho). Para PDF elige 'Microsoft Print to PDF' o Archivo > Exportar > PDF.
C11: ¿Con qué versiones de Excel funciona? | D11: Excel 2016, 2019, 2021 y Microsoft 365 (Windows y Mac). Funciona en LibreOffice y Google Sheets, aunque algunas gráficas y formatos pueden verse distintos.
C12: ¿Puedo cambiar la letra? | D12: El diseño usa la fuente Arial, disponible en Windows, Mac y Google Sheets. Si necesitas otra, selecciona todo (Ctrl+E) y cambia la fuente; no afecta el funcionamiento.
C13: ¿Puedo usarlo en varias empresas o por varios años? | D13: Sí. Guarda una copia del archivo por empresa o por periodo (Archivo > Guardar como) y deja el original en blanco como plantilla maestra.
B15: GLOSARIO
C16: MOI | D16: Monto original de la inversión.
C17: DEPRECIACIÓN | D17: Pérdida de valor por uso o paso del tiempo.
C18: VALOR EN LIBROS | D18: MOI - depreciación acumulada.
B20: LISTA DE VERIFICACIÓN (marca ☑ al completar)
B21: ☐ | C21: Activo etiquetado
B22: ☐ | C22: Factura archivada
B23: ☐ | C23: Responsable asignado
B24: ☐ | C24: Inventario físico anual realizado
